Workbook
Name _____________________________tu1: #REF!
Name ____________________________tu1: #REF!
Name ___________________________tu1: #REF!
Name __________________________tu1: #REF!
Name _________________________tu1: #REF!
Name ________________________tu1: #REF!
Name _______________________tu1: #REF!
Name ______________________tu1: #REF!
Name _____________________tu1: #REF!
Name ____________________tu1: #REF!
Name ___________________tu1: #REF!
Name __________________tu1: #REF!
Name _________________tu1: #REF!
Name ________________tu1: #REF!
Name _______________tu1: #REF!
Name ______________tu1: #REF!
Name _____________tu1: #REF!
Name ____________tu1: #REF!
Name ___________tu1: #REF!
Name __________tu1: #REF!
Name _________tu1: #REF!
Name ________tu1: #REF!
Name _______HAL12: #REF!
Name _______tu1: #REF!
Name ______HAL12: #REF!
Name ______kod1: #REF!
Name ______sum1: #REF!
Name ______tu1: #REF!
Name _____AF3: MATCH(0.01,'[1]CAPEX BE'!End_Bal,-1)+1
Name _____af4: MATCH(0.01,'[1]CAPEX BE'!End_Bal,-1)+1
Name _____ALT1: #REF!
Name _____ALT2: #REF!
Name _____ALT3: #REF!
Name _____ALT4: #REF!
Name _____ALT5: #REF!
Name _____ALT6: #REF!
Name _____ALT7: #REF!
Name _____ALT8: #REF!
Name _____ALT9: #REF!
Name _____CAD1: #REF!
Name _____DLR1: #REF!
Name _____HAL12: #REF!
Name _____KL33: #REF!
Name _____KL331: #REF!
Name _____kod1: #REF!
Name _____MEN1: #REF!
Name _____Mov2: [2]Revenue!$J$7:$R$187
Name _____PTL1: #REF!
Name _____qwe1: MATCH(0.01,'[1]CAPEX BE'!End_Bal,-1)+1
Name _____RP1: #REF!
Name _____SDM1: #REF!
Name _____sum1: #REF!
Name _____tu1: #REF!
Name _____z2: MATCH(0.01,'[1]CAPEX BE'!End_Bal,-1)+1
Name ____DLR1: #REF!
Name ____HAL12: #REF!
Name ____kii44: #REF!
Name ____kod1: #REF!
Name ____MNP0205: #REF!
Name ____Mov2: [2]Revenue!$J$7:$R$187

Sheet Model Design
B2: MODEL DESIGN — PT JAMINAN PEMBIAYAAN ASKRINDO SYARIAH
B3: Financial Performance Workbook | Periode Mei 2026 | CFI-Standard Model Design Framework
B4: CONFIDENTIAL — Internal Use Only
B6: 1. MODEL OBJECTIVE (Output-First Design)
B7: Decision This Model Answers: | C7: How is JPAS performing against RKAP 2026, and what are the key risk drivers affecting profitability?
B8: Primary Audience: | C8: Management / Komisaris / OJK Reporting
B9: Periodicity: | C9: Monthly (YTD actuals vs. RKAP budget)
B10: Currency & Units: | C10: IDR in Jutaan Rupiah (Rp Juta)
B12: 2. MODEL CHECKS (Display on Cover)
B13: Check | C13: Formula / Source | D13: Status
B14: Balance Sheet Balanced? | C14: = Total Aset − (Total Liabilitas + Total Ekuitas) = 0 | D14: → Link from Summary BS KONSOL
B15: Laba Rugi ties to Ekuitas (BS)? | C15: = Laba Neto in IS = Perubahan Retained Earnings in BS | D15: → Verify cross-statement link
B16: Cash Flow ties to Kas (BS)? | C16: = Ending Cash in CFS = Kas & Setara Kas in BS | D16: → Link from CASH FLOW Mei 2026
B17: RKAP Utilization Within Limit? | C17: = YTD Realisasi / RKAP s/d Period ≤ 100% | D17: → Flag if >100% (overspend)
B18: Gearing Ratio Within Limit? | C18: = As per OJK/regulatory threshold (typical: ≤40x) | D18: → Link from Gearing Ratio sheet
B20: 3. MODULAR BUILDING BLOCKS — TAB INVENTORY
B21: Block Type | C21: Tab Name | D21: Purpose | E21: Feeds Into
B22: COVER / DESIGN | C22: Model Design (this sheet) | D22: Objective, checks, tab map, driver framework | E22: —
B23: DASHBOARD / OUTPUT | C23: Lap. LR-Kinerja Mei 2026 | D23: Comprehensive P&L performance vs. RKAP & prior year | E23: Management report
B24: DASHBOARD / OUTPUT | C24: Lap. PK - Kinerja Mei 2026 | D24: Balance sheet performance KPIs | E24: Management report
B25: DASHBOARD / OUTPUT | C25: Lap. AK-Kinerja Mei 2026 | D25: Cash flow & liquidity KPIs | E25: Management report
B26: FINANCIAL STATEMENT | C26: Summary PL KONSOL Mei 2026 | D26: Consolidated P&L: YTD, MoM, YoY, vs. RKAP | E26: Lap. LR-Kinerja; Dashboard
B27: FINANCIAL STATEMENT | C27: Summary BS KONSOL Mei 2026 | D27: Consolidated balance sheet | E27: Lap. PK-Kinerja; BS Check
B28: FINANCIAL STATEMENT | C28: CASH FLOW Mei 2026 | D28: Operating / Investing / Financing cash flows | E28: Lap. AK-Kinerja; Cash Check
B29: OPERATING SCHEDULE | C29: Hasil Underwriting | D29: Underwriting result: IJK, claims, net UW income | E29: Summary PL KONSOL
B30: OPERATING SCHEDULE | C30: Input HUW | D30: Raw underwriting input assumptions / data entry | E30: Hasil Underwriting
B31: OPERATING SCHEDULE | C31: Cadangan Teknis | D31: Technical reserves (IBNR, unearned premium equiv.) | E31: Summary BS; Summary PL
B32: OPERATING SCHEDULE | C32: Beban Usaha | D32: Operating expense detail by line item | E32: Summary PL KONSOL; Opex
... B46: BUSINESS VOLUME | C46: KUR | D46: KUR (Kredit Usaha Rakyat) program volume & performance | E46: Hasil Underwriting; Summary PL
B48: 4. KEY DRIVERS — Volatile & High-Impact Inputs
B49: Driver | C49: Volatile? | D49: High Impact? | E49: Is a Driver? | F49: Source Tab
B50: Imbal Jasa Kafalah (IJK) volume | C50: YES | D50: YES | E50: ✓ DRIVER | F50: Input HUW; Per Bank Per COB
B51: Klaim / Tawidh rate (loss ratio) | C51: YES | D51: YES | E51: ✓ DRIVER | F51: Hasil Underwriting; Cadangan Teknis
B52: Beban penjaminan ulang (re-kafalah cost) | C52: Moderate | D52: YES | E52: ✓ DRIVER | F52: Input HUW; Summary PL
B53: Cadangan teknis (IBNR / unearned) | C53: YES | D53: YES | E53: ✓ DRIVER | F53: Cadangan Teknis
B54: Investment return (yield on portfolio) | C54: Moderate | D54: YES | E54: ✓ DRIVER | F54: Investasi Mei 2026
B55: Opex / Beban usaha total | C55: Moderate | D55: Moderate | E55: ✓ DRIVER | F55: Beban Usaha; Opex
B56: Gearing ratio (regulatory limit) | C56: YES | D56: YES | E56: ✓ DRIVER | F56: Gearing Ratio
B57: Tax rate | C57: NO | D57: Moderate | E57: — Not a driver | F57: Stable per regulation
B58: Subrogasi recovery rate | C58: YES | D58: LOW | E58: — Monitor only | F58: Subrogasi + SHS
B60: 5. SCENARIO FRAMEWORK — Driver Switch Setup
B61: DRIVER SWITCH: | C61: 1 | D61: ← Change: 1=Best, 2=Base, 3=Worst
B62: Active Scenario: | C62: =CHOOSE(C61,"BEST CASE ↑","BASE CASE ►","WORST CASE ↓")
B64: Driver | C64: Best Case | D64: Base Case | E64: Worst Case | F64: Active (CHOOSE)
B65: IJK Growth (YoY) | C65: 0.15 | D65: 0.05 | E65: -0.05 | F65: =CHOOSE($C$61,C65,D65,E65)
B66: Loss Ratio (Klaim/IJK) | C66: 0.5 | D66: 0.65 | E66: 0.8 | F66: =CHOOSE($C$61,C66,D66,E66)
B67: Investment Yield | C67: 0.065 | D67: 0.055 | E67: 0.04 | F67: =CHOOSE($C$61,C67,D67,E67)
B68: Opex Growth (vs. RKAP) | C68: -0.05 | D68: 0 | E68: 0.08 | F68: =CHOOSE($C$61,C68,D68,E68)
B69: Cadangan Teknis Rate | C69: 0.08 | D69: 0.12 | E69: 0.18 | F69: =CHOOSE($C$61,C69,D69,E69)
B71: 6. SINGLE ENTRY PRINCIPLE — Input Flow Rules
B72: ❌ WRONG — Link in Series: | C72: IJK (Input HUW) → Hasil UW → Summary PL → Lap. LR [Breaks if middle tab deleted]
B73: ✅ RIGHT — Link to Source: | C73: IJK (Input HUW) ← Hasil UW | IJK (Input HUW) ← Summary PL | IJK (Input HUW) ← Lap. LR
B74: Rule: | C74: Every assumption entered ONCE in source tab. All tabs reference the source directly, never chain-link.
B76: 7. MODEL DESIGN CHECKLIST
B77: ☐ Decision / question model answers is clearly defined
B78: ☐ Dashboard outputs, KPIs, and charts identified (output-first)
B79: ☐ All required schedules mapped (Tab Inventory complete)
B80: ☐ Unnecessary tabs / complexity excluded
B81: ☐ Model drivers identified (volatile + high-impact)
B82: ☐ Three scenario values prepared for each driver (Best/Base/Worst)
B83: ☐ Driver switch cell set up (C61 on this sheet)
B84: ☐ All assumptions sourced to Input HUW or this sheet (single entry)
B85: ☐ Balance sheet check formula wired
B86: ☐ Cash tie-out (CFS ending cash = BS kas) verified
B87: ☐ Gearing ratio within OJK regulatory limit
... B91: 8. COLOR CODING LEGEND
B92: Blue text | C92: Hardcoded inputs — numbers user changes for scenarios
B93: Black text | C93: All formulas and calculations
B94: Green text | C94: Cross-sheet links within this workbook
B95: Red text | C95: External links to other files
B96: Yellow fill | C96: Key assumptions needing attention / cells to update
B98: Model Version: | C98: v1.0 — June 2026
B99: Last Updated: | C99: 2026-06-19
B100: Author: | C100: Finance Division — JPAS

Sheet Summary PL KONSOL Mei 2026
A1: Laporan Laba Rugi Konsolidasi Askrindo dan Entitas Anak
A2: (dalam Jutaan Rupiah)
A3: Keterangan | D3: Realisasi | F3: Realisasi | H3: Realisasi | J3: %YoY | L3: Realisasi | N3: Realisasi | P3: %MoM | R3: RKAP s/d Mei 2026 | T3: % terhadap RKAP s/d Januari 2026 | V3: RKAP 2026 | X3: % terhadap RKAP 2026
D4: s/d April 2026 | F4: s/d Mei 2026 | H4: s/d Mei 2025 | L4: April 2026 | N4: Mei 2026
A6: Pendapatan Underwriting | D6: 208154.21 | E6: =SUM(E8:E12) | F6: =SUM(F8:F12) | H6: 212565.69 | J6: =F6/H6-1 | L6: 57323.966 | N6: =F6-D6 | P6: =N6/L6-1 | R6: =SUM(R8:R12) | T6: =F6/R6 | V6: =SUM(V8:V12) | X6: =F6/V6
D7: 0 | F7: =N7 | H7: 0 | L7: 0 | N7: 0
A8: Pendapatan Jasa Penjaminan (IJK) | D8: 328122.62 | F8: ='Lap. LR-Kinerja Mei 2026'!F9 | H8: 283047.36 | J8: =F8/H8-1 | L8: 78485.329 | N8: =F8-D8 | P8: =N8/L8-1 | R8: 361609.38 | T8: =F8/R8 | V8: ='Lap. LR-Kinerja Mei 2026'!E9 | X8: =F8/V8
A9: Beban Penjaminan Ulang | D9: -79897.189 | F9: ='Lap. LR-Kinerja Mei 2026'!F11 | H9: -72165.752 | J9: =F9/H9-1 | L9: -18445.639 | N9: =F9-D9 | P9: =N9/L9-1 | R9: -94444.697 | T9: =F9/R9 | V9: ='Lap. LR-Kinerja Mei 2026'!E11 | X9: =F9/V9
A10: Komisi penjaminan ulang | D10: 22277.016 | F10: ='Lap. LR-Kinerja Mei 2026'!F12+'Lap. LR-Kinerja Mei 2026'!F13 | H10: 25400.057 | J10: =F10/H10-1 | L10: 5896.4258 | N10: =F10-D10 | P10: =N10/L10-1 | R10: 19643.534 | T10: =F10/R10 | V10: ='Lap. LR-Kinerja Mei 2026'!E12+'Lap. LR-Kinerja Mei 2026'!E13 | X10: =F10/V10
A11: (Kenaikan) Penurunan IJK yang Belum Merupakan Pendapatan | D11: -62379.684 | F11: ='Lap. LR-Kinerja Mei 2026'!F14 | H11: -23756.249 | J11: =F11/H11-1 | L11: -8619.8818 | N11: =F11-D11 | P11: =N11/L11-1 | R11: -38853.236 | T11: =F11/R11 | V11: ='Lap. LR-Kinerja Mei 2026'!E14 | X11: =F11/V11
A12: Pendapatan Underwriting Lain | D12: 31.448552 | F12: ='Lap. LR-Kinerja Mei 2026'!F15 | H12: 40.273 | J12: 0 | L12: 7.732 | N12: =F12-D12 | P12: =N12/L12-1 | R12: 54.460224 | T12: =F12/R12 | V12: ='Lap. LR-Kinerja Mei 2026'!E15 | X12: =F12/V12
A14: Beban Underwriting | D14: 138400.76 | F14: =SUM(F16:F22) | H14: 112554.02 | J14: =F14/H14-1 | L14: 27550.756 | N14: =F14-D14 | P14: =N14/L14-1 | R14: =SUM(R16:R22) | T14: =F14/R14 | V14: =SUM(V16:V22) | X14: =F14/V14
A16: Ta'widh Bruto | D16: 188989.84 | F16: ='Lap. LR-Kinerja Mei 2026'!F19 | H16: 156690.22 | J16: =F16/H16-1 | L16: 42288.658 | N16: =F16-D16 | P16: =N16/L16-1 | R16: 208980.21 | T16: =F16/R16 | V16: ='Lap. LR-Kinerja Mei 2026'!E19 | X16: =F16/V16
A17: Ta'widh Reasuransi | D17: -60256.244 | F17: ='Lap. LR-Kinerja Mei 2026'!F20 | H17: -52659.469 | J17: =F17/H17-1 | L17: -13833.969 | N17: =F17-D17 | P17: =N17/L17-1 | R17: -67864.798 | T17: =F17/R17 | V17: ='Lap. LR-Kinerja Mei 2026'!E20 | X17: =F17/V17
A18: Kenaikan (Penurunan) Estimasi Tawidh Retensi Sendiri | D18: 19968.458 | F18: ='Lap. LR-Kinerja Mei 2026'!F24 | H18: 40617.292 | J18: =F18/H18-1 | L18: 1868.4391 | N18: =F18-D18 | P18: =N18/L18-1 | R18: 21007.135 | T18: =F18/R18 | V18: ='Lap. LR-Kinerja Mei 2026'!E24 | X18: =F18/V18
A19: Pendapatan Recoveries - bersih | D19: -19650.767 | F19: ='Lap. LR-Kinerja Mei 2026'!F23 | H19: -40708.37 | J19: =F19/H19-1 | L19: -5277.2595 | N19: =F19-D19 | P19: =N19/L19-1 | R19: -18524.823 | T19: =F19/R19 | V19: ='Lap. LR-Kinerja Mei 2026'!E23 | X19: =F19/V19
A20: Beban Komisi | D20: 10932.712 | F20: ='Lap. LR-Kinerja Mei 2026'!F21 | H20: 7854.2954 | J20: =F20/H20-1 | L20: 1564.806 | N20: =F20-D20 | P20: =N20/L20-1 | R20: 11804.442 | T20: =F20/R20 | V20: ='Lap. LR-Kinerja Mei 2026'!E21 | X20: =F20/V20
A21: Beban akuisisi tangguhan | D21: -2283.2809 | F21: ='Lap. LR-Kinerja Mei 2026'!F22 | H21: -134.76586 | J21: =F21/H21-1 | L21: 882.38976 | N21: =F21-D21 | P21: =N21/L21-1 | R21: -1444.2408 | T21: =F21/R21 | V21: ='Lap. LR-Kinerja Mei 2026'!E22 | X21: =F21/V21
A22: Beban Underwriting Lain | D22: 700.04037 | F22: ='Lap. LR-Kinerja Mei 2026'!F25 | H22: 894.81787 | J22: =F22/H22-1 | L22: 57.69153 | N22: =F22-D22 | P22: =IFERROR(N22/L22-1,"") | R22: 1294.8414 | T22: =F22/R22 | V22: ='Lap. LR-Kinerja Mei 2026'!E25 | X22: =F22/V22
A24: Hasil Underwriting Neto | D24: 69753.455 | F24: =F6-F14 | H24: 100011.67 | J24: =F24/H24-1 | L24: 29773.21 | N24: =F24-D24 | P24: =N24/L24-1 | R24: =R6-R14 | T24: =F24/R24 | V24: =V6-V14 | X24: =F24/V24
A26: Hasil Investasi | D26: 50162.338 | F26: ='Lap. LR-Kinerja Mei 2026'!F29 | H26: 59202.376 | J26: =F26/H26-1 | L26: 12425.926 | N26: =F26-D26 | P26: =N26/L26-1 | R26: 63701.826 | T26: =F26/R26 | V26: ='Lap. LR-Kinerja Mei 2026'!E29 | X26: =F26/V26
A28: Beban Pemasaran | D28: 4349.7301 | F28: ='Lap. LR-Kinerja Mei 2026'!F32 | H28: 4712.1651 | J28: =F28/H28-1 | L28: 1082.7826 | N28: =F28-D28 | P28: =N28/L28-1 | R28: 5808.4799 | T28: =F28/R28 | V28: ='Lap. LR-Kinerja Mei 2026'!E32 | X28: =F28/V28
A29: Beban Umum | D29: 34312.458 | F29: ='Lap. LR-Kinerja Mei 2026'!F33 | H29: 39671.097 | J29: =F29/H29-1 | L29: 10307.703 | N29: =F29-D29 | P29: =N29/L29-1 | R29: 47265.863 | T29: =F29/R29 | V29: ='Lap. LR-Kinerja Mei 2026'!E33 | X29: =F29/V29
A30: Beban Administrasi | D30: 5846.7861 | F30: ='Lap. LR-Kinerja Mei 2026'!F34 | H30: 7210.0197 | J30: =F30/H30-1 | L30: 1807.035 | N30: =F30-D30 | P30: =N30/L30-1 | R30: 10296.714 | T30: =F30/R30 | V30: ='Lap. LR-Kinerja Mei 2026'!E34 | X30: =F30/V30
A31: Beban Penyusutan & Amortasi | D31: 4728.0455 | F31: ='Lap. LR-Kinerja Mei 2026'!F35 | H31: 6389.3085 | J31: =F31/H31-1 | L31: 1234.7307 | N31: =F31-D31 | P31: =N31/L31-1 | R31: 6639.2721 | T31: =F31/R31 | V31: ='Lap. LR-Kinerja Mei 2026'!E35 | X31: =F31/V31
A32: Total Beban Usaha | D32: 49237.019 | E32: =SUM(E28:E31) | F32: =SUM(F28:F31) | G32: =SUM(G28:G31) | H32: 57982.591 | J32: =F32/H32-1 | L32: 14432.252 | M32: =SUM(M28:M31) | N32: =F32-D32 | P32: =N32/L32-1 | R32: 70010.329 | T32: =F32/R32 | V32: =SUM(V28:V31) | X32: =F32/V32
A34: Laba Usaha | D34: 70678.775 | F34: =F24+F26-F32 | H34: 101231.46 | J34: =F34/H34-1 | L34: 27766.884 | N34: =F34-D34 | P34: =N34/L34-1 | R34: =R24+R26-R32 | T34: =F34/R34 | V34: =(V24+V26)-V32 | X34: =F34/V34
A36: (Beban) Pendapatan Lain-lain | D36: -6495.4726 | F36: ='Lap. LR-Kinerja Mei 2026'!F40 | H36: -7016.9091 | J36: =F36/H36-1 | L36: -1751.0852 | N36: =F36-D36 | P36: =N36/L36-1 | R36: -7879.2136 | T36: =F36/R36 | V36: ='Lap. LR-Kinerja Mei 2026'!E40 | X36: =F36/V36
A38: Zakat | D38: 1604.5825 | F38: ='Lap. LR-Kinerja Mei 2026'!F44 | H38: 2355.3637 | J38: =F38/H38-1 | L38: 650.39498 | N38: =F38-D38 | P38: =N38/L38-1 | R38: 1964.2239 | T38: =F38/R38 | V38: ='Lap. LR-Kinerja Mei 2026'!E44 | X38: =F38/V38
A40: Laba Sebelum Pajak | D40: 62578.719 | F40: =F34+F36-F38 | H40: 91859.182 | J40: =F40/H40-1 | L40: 25365.404 | N40: =F40-D40 | P40: =N40/L40-1 | R40: 76604.734 | T40: =F40/R40 | V40: =V34+V36-V38 | X40: =F40/V40
A42: Pajak Penghasilan | D42: 11552.994 | F42: ='Lap. LR-Kinerja Mei 2026'!F50 | H42: 15074.327 | J42: =F42/H42-1 | L42: 4797.3463 | N42: =F42-D42 | P42: =N42/L42-1 | R42: 14554.899 | T42: =F42/R42 | V42: ='Lap. LR-Kinerja Mei 2026'!E50 | X42: =F42/V42
A44: Laba Setelah Pajak | D44: 51025.725 | F44: =F40-F42 | H44: 76784.855 | J44: =F44/H44-1 | L44: 20568.058 | N44: =F44-D44 | P44: =N44/L44-1 | R44: 62049.835 | T44: =F44/R44 | V44: =V40-V42 | X44: =F44/V44

Sheet Summary BS KONSOL Mei 2026
A1: Laporan Posisi Keuangan Konsolidasi Askrindo dan Entitas Anak
A2: (dalam Jutaan Rupiah)
A3: Keterangan | D3: Realisasi | F3: Realisasi | H3: Audited | I3: Realisasi | K3: %YoY | M3: Realisasi | O3: Realisasi | Q3: %MoM | S3: RKAP s/d Mei 2026 | U3: % terhadap RKAP s/d Mei 2026 | W3: RKAP 2026 | Y3: % terhadap RKAP 2026
D4: Per April 2026 | F4: Per Mei 2026 | H4: s/d Mei '22 | I4: Per Mei 2025 | M4: April 2026 | O4: Mei 2026
A6: ASET | D6: 3403950.7 | F6: =SUM(F8:F23) | I6: 3193491.6 | K6: =F6/I6-1 | M6: 64843.671 | O6: =SUM(O8:O24) | Q6: =IFERROR((O6/M6-1),"") | S6: =SUM(S8:S23) | U6: =IFERROR(F6/S6,"") | W6: =SUM(W8:W23) | Y6: =IFERROR(F6/W6,"")
Q7: =IFERROR((O7/M7-1),"") | U7: =IFERROR(F7/S7,"") | Y7: =IFERROR(F7/W7,"")
A8: Kas dan bank | D8: 81962.748 | F8: ='Lap. PK - Kinerja Mei 2026'!E11+'Lap. PK - Kinerja Mei 2026'!E12 | I8: 117308.06 | K8: =IFERROR(F8/I8-1,"") | M8: -1299.8155 | O8: =F8-D8 | Q8: =IFERROR((O8/M8-1),"") | S8: 111761.85 | U8: =IFERROR(F8/S8,"") | W8: 120923.64 | Y8: =IFERROR(F8/W8,"")
A9: Piutang imbal jasa kafalah | D9: 2006.4061 | F9: ='Lap. PK - Kinerja Mei 2026'!E13+'Lap. PK - Kinerja Mei 2026'!E14 | I9: 2831.5346 | K9: =IFERROR(F9/I9-1,"") | M9: 543.38737 | O9: =F9-D9 | Q9: =IFERROR((O9/M9-1),"") | S9: 2723.466 | U9: =IFERROR(F9/S9,"") | W9: 2959.6378 | Y9: =IFERROR(F9/W9,"")
A10: Piutang ta'widh | D10: 76504.003 | F10: ='Lap. PK - Kinerja Mei 2026'!E15+'Lap. PK - Kinerja Mei 2026'!E16 | I10: 43262.629 | K10: =IFERROR(F10/I10-1,"") | M10: 12409.392 | O10: =F10-D10 | Q10: =IFERROR((O10/M10-1),"") | S10: 58047.528 | U10: =IFERROR(F10/S10,"") | W10: 56682.869 | Y10: =IFERROR(F10/W10,"")
A11: Piutang investasi | D11: 34359.264 | F11: ='Lap. PK - Kinerja Mei 2026'!E17 | I11: 25479.052 | K11: =IFERROR(F11/I11-1,"") | M11: 3479.7919 | O11: =F11-D11 | Q11: =IFERROR((O11/M11-1),"") | S11: 29857.589 | U11: =IFERROR(F11/S11,"") | W11: 31921.341 | Y11: =IFERROR(F11/W11,"")
A12: Aset Reasuransi | D12: 653784.3 | F12: ='Lap. PK - Kinerja Mei 2026'!E18 | I12: 724218.71 | K12: =IFERROR(F12/I12-1,"") | M12: 15763.458 | O12: =F12-D12 | Q12: =IFERROR((O12/M12-1),"") | S12: 768023.6 | U12: =IFERROR(F12/S12,"") | W12: 847155.3 | Y12: =IFERROR(F12/W12,"")
A13: Biaya akuisisi yang ditangguhkan | D13: 38412.166 | F13: ='Lap. PK - Kinerja Mei 2026'!E19 | I13: 34915.418 | K13: =IFERROR(F13/I13-1,"") | M13: -882.38976 | O13: =F13-D13 | Q13: =IFERROR((O13/M13-1),"") | S13: 35488.632 | U13: =IFERROR(F13/S13,"") | W13: 37638.341 | Y13: =IFERROR(F13/W13,"")
A14: Biaya dibayar dimuka | D14: 13719.294 | F14: ='Lap. PK - Kinerja Mei 2026'!E20 | I14: 12088.355 | K14: =IFERROR(F14/I14-1,"") | M14: 123.77778 | O14: =F14-D14 | Q14: =IFERROR((O14/M14-1),"") | S14: 11998.819 | U14: =IFERROR(F14/S14,"") | W14: 11888.738 | Y14: =IFERROR(F14/W14,"")
A15: Pajak dibayar dimuka | D15: 1.9073486e-11 | F15: ='Lap. PK - Kinerja Mei 2026'!E21 | I15: 1.9073486e-11 | K15: =IFERROR(F15/I15-1,"") | M15: 0 | O15: =F15-D15 | Q15: =IFERROR((O15/M15-1),"") | S15: 0 | U15: =IFERROR(F15/S15,"") | W15: 0 | Y15: =IFERROR(F15/W15,"")
A16: Investasi | K16: =IFERROR(F16/I16-1,"")
A17: Deposito berjangka mudharabah | D17: 432300 | F17: ='Lap. PK - Kinerja Mei 2026'!E23 | I17: 467050 | K17: =IFERROR(F17/I17-1,"") | M17: -114900 | O17: =F17-D17 | Q17: =IFERROR((O17/M17-1),"") | S17: 454400 | U17: =IFERROR(F17/S17,"") | W17: 454400 | Y17: =IFERROR(F17/W17,"")
A18: Reksadana tersedia untuk dijual | D18: 100625.15 | F18: ='Lap. PK - Kinerja Mei 2026'!E24 | I18: 80748.598 | K18: =IFERROR(F18/I18-1,"") | M18: 44987.618 | O18: =F18-D18 | Q18: =IFERROR((O18/M18-1),"") | S18: 127056.67 | U18: =IFERROR(F18/S18,"") | W18: 142246.67 | Y18: =IFERROR(F18/W18,"")
A19: Surat Berharga Syariah Negara | D19: 1916908.5 | F19: ='Lap. PK - Kinerja Mei 2026'!E25 | I19: 1636665 | K19: =IFERROR(F19/I19-1,"") | M19: 96209.504 | O19: =F19-D19 | Q19: =IFERROR((O19/M19-1),"") | S19: 1887212.7 | U19: =IFERROR(F19/S19,"") | W19: 2034233.9 | Y19: =IFERROR(F19/W19,"")
A20: Aset pajak tangguhan | D20: 22839.203 | F20: ='Lap. PK - Kinerja Mei 2026'!E26 | I20: 13872.599 | K20: =IFERROR(F20/I20-1,"") | M20: 8966.6037 | O20: =F20-D20 | Q20: =IFERROR((O20/M20-1),"") | S20: 13872.599 | U20: =IFERROR(F20/S20,"") | W20: 13872.599 | Y20: =IFERROR(F20/W20,"")
A21: Aset tetap | D21: 26990.454 | F21: ='Lap. PK - Kinerja Mei 2026'!E27 | I21: 30460.163 | K21: =IFERROR(F21/I21-1,"") | M21: -476.74334 | O21: =F21-D21 | Q21: =IFERROR((O21/M21-1),"") | S21: 32231.263 | U21: =IFERROR(F21/S21,"") | W21: 26433.967 | Y21: =IFERROR(F21/W21,"")
A22: Aset tidak berwujud | D22: 1932.4396 | F22: ='Lap. PK - Kinerja Mei 2026'!E28 | I22: 2501.7194 | K22: =IFERROR(F22/I22-1,"") | M22: -76.868475 | O22: =F22-D22 | Q22: =IFERROR((O22/M22-1),"") | S22: 3459.5557 | U22: =IFERROR(F22/S22,"") | W22: 6637.5592 | Y22: =IFERROR(F22/W22,"")
A23: Aset lain-lain | D23: 1606.8143 | F23: ='Lap. PK - Kinerja Mei 2026'!E29 | I23: 2089.7957 | K23: =IFERROR(F23/I23-1,"") | M23: -4.0447445 | O23: =F23-D23 | Q23: 1 | S23: 3269.1219 | U23: =IFERROR(F23/S23,"") | W23: 3452.1927 | Y23: =IFERROR(F23/W23,"")
Q24: =IFERROR((O24/M24-1),"") | U24: =IFERROR(F24/S24,"") | Y24: =IFERROR(F24/W24,"")
Q25: =IFERROR((O25/M25-1),"") | U25: =IFERROR(F25/S25,"") | Y25: =IFERROR(F25/W25,"")
A26: LIABILITAS | D26: 2215684.3 | F26: =SUM(F28:F40) | I26: 2119296.8 | K26: =F26/I26-1 | M26: 37997.29 | O26: =SUM(O28:O41) | Q26: =IFERROR((O26/M26-1),"") | S26: =SUM(S28:S40) | U26: =IFERROR(F26/S26,"") | W26: =SUM(W28:W40) | Y26: =IFERROR(F26/W26,"")
Q27: =IFERROR((O27/M27-1),"") | U27: =IFERROR(F27/S27,"") | Y27: =IFERROR(F27/W27,"")
A28: Utang tawidh | D28: 140.22234 | F28: ='Lap. PK - Kinerja Mei 2026'!E35 | I28: 14437.973 | K28: 1 | M28: 123.47217 | O28: =F28-D28 | Q28: =IFERROR((O28/M28-1),"") | S28: 2104.7402 | U28: =IFERROR(F28/S28,"") | W28: 2145.9411 | Y28: =IFERROR(F28/W28,"")
A29: Utang penjaminan ulang | D29: 54666.206 | F29: ='Lap. PK - Kinerja Mei 2026'!E36 | I29: 33414.983 | K29: =IFERROR(F29/I29-1,"") | M29: 10324.837 | O29: =F29-D29 | Q29: =IFERROR((O29/M29-1),"") | S29: 45126.271 | U29: =IFERROR(F29/S29,"") | W29: 50512.811 | Y29: =IFERROR(F29/W29,"")
A30: Utang Komisi | D30: 7701.85 | F30: ='Lap. PK - Kinerja Mei 2026'!E37 | I30: 8363.863 | K30: =IFERROR(F30/I30-1,"") | M30: -37.374228 | O30: =F30-D30 | Q30: =IFERROR((O30/M30-1),"") | S30: 8593.9397 | U30: =IFERROR(F30/S30,"") | W30: 9136.4604 | Y30: =IFERROR(F30/W30,"")
A31: Pendapatan diterima dimuka | D31: 27854.927 | F31: ='Lap. PK - Kinerja Mei 2026'!E38 | I31: 31953.425 | K31: =IFERROR(F31/I31-1,"") | M31: 1849.1549 | O31: =F31-D31 | Q31: =IFERROR((O31/M31-1),"") | S31: 33478.039 | U31: =IFERROR(F31/S31,"") | W31: 31937.209 | Y31: =IFERROR(F31/W31,"")
A32: Utang zakat | D32: 4647.737 | F32: ='Lap. PK - Kinerja Mei 2026'!E39 | I32: 7421.6869 | K32: =IFERROR(F32/I32-1,"") | M32: 733.35217 | O32: =F32-D32 | Q32: =IFERROR((O32/M32-1),"") | S32: 8320.7672 | U32: =IFERROR(F32/S32,"") | W32: 7513.1761 | Y32: =IFERROR(F32/W32,"")
A33: Utang pajak | D33: 10838.232 | F33: ='Lap. PK - Kinerja Mei 2026'!E40 | I33: 10984.789 | K33: =IFERROR(F33/I33-1,"") | M33: 3055.5035 | O33: =F33-D33 | Q33: =IFERROR((O33/M33-1),"") | S33: 18912.062 | U33: =IFERROR(F33/S33,"") | W33: 18698.064 | Y33: =IFERROR(F33/W33,"")
A34: Beban akrual | D34: 41924.337 | F34: ='Lap. PK - Kinerja Mei 2026'!E41 | I34: 37009.013 | K34: =IFERROR(F34/I34-1,"") | M34: -3221.6797 | O34: =F34-D34 | Q34: =IFERROR((O34/M34-1),"") | S34: 54847.885 | U34: =IFERROR(F34/S34,"") | W34: 62693.418 | Y34: =IFERROR(F34/W34,"")
A35: Estimasi ta'widh retensi sendiri | D35: 463614.54 | F35: ='Lap. PK - Kinerja Mei 2026'!E42 | I35: 466670.28 | K35: =IFERROR(F35/I35-1,"") | M35: 20270.366 | O35: =F35-D35 | Q35: =IFERROR((O35/M35-1),"") | S35: 543869.2 | U35: =IFERROR(F35/S35,"") | W35: 657950.35 | Y35: =IFERROR(F35/W35,"")
A36: Estimasi ujrah yang belum merupakan pendapatan | D36: 1465413.5 | F36: ='Lap. PK - Kinerja Mei 2026'!E43 | I36: 1363677.9 | K36: =IFERROR(F36/I36-1,"") | M36: 5981.413 | O36: =F36-D36 | Q36: =IFERROR((O36/M36-1),"") | S36: 1453609.5 | U36: =IFERROR(F36/S36,"") | W36: 1502201.3 | Y36: =IFERROR(F36/W36,"")
A37: Pendapatan komisi yang ditangguhkan | D37: 128878.16 | F37: ='Lap. PK - Kinerja Mei 2026'!E44 | I37: 133230.32 | K37: =IFERROR(F37/I37-1,"") | M37: -1349.8138 | O37: =F37-D37 | Q37: =IFERROR((O37/M37-1),"") | S37: 141421.14 | U37: =IFERROR(F37/S37,"") | W37: 140161.51 | Y37: =IFERROR(F37/W37,"")
A38: Liabilitas imbalan kerja jangka panjang | D38: 246.29405 | F38: ='Lap. PK - Kinerja Mei 2026'!E45 | I38: 133.92676 | K38: =IFERROR(F38/I38-1,"") | M38: 112.36729 | O38: =F38-D38 | Q38: =IFERROR((O38/M38-1),"") | S38: 133.92676 | U38: =IFERROR(F38/S38,"") | W38: 133.92676 | Y38: =IFERROR(F38/W38,"")
A39: Utang Deviden | D39: 0 | F39: 0 | I39: 1156.9619 | K39: =IFERROR(F39/I39-1,"") | M39: 0 | O39: =F39-D39 | Q39: =IFERROR((O39/M39-1),"") | S39: 0 | U39: =IFERROR(F39/S39,"") | W39: 0 | Y39: =IFERROR(F39/W39,"")
A40: Utang lain-lain | D40: 9758.3049 | F40: ='Lap. PK - Kinerja Mei 2026'!E47 | I40: 10841.712 | K40: =IFERROR(F40/I40-1,"") | M40: 155.69163 | O40: =F40-D40 | Q40: =IFERROR((O40/M40-1),"") | S40: 10816.667 | U40: =IFERROR(F40/S40,"") | W40: 10977.528 | Y40: =IFERROR(F40/W40,"")
Q41: =IFERROR((O41/M41-1),"") | U41: =IFERROR(F41/S41,"") | Y41: =IFERROR(F41/W41,"")
Q42: =IFERROR((O42/M42-1),"") | U42: =IFERROR(F42/S42,"") | Y42: =IFERROR(F42/W42,"")
A43: EKUITAS | D43: 1188266.5 | F43: =SUM(F45:F50) | H43: =SUM(H45:H50) | I43: 1074194.8 | K43: =F43/I43-1 | M43: 26846.381 | O43: =SUM(O45:O50) | Q43: =IFERROR((O43/M43-1),"") | S43: =SUM(S45:S50) | U43: =IFERROR(F43/S43,"") | W43: =SUM(W45:W50) | Y43: =IFERROR(F43/W43,"")
Q44: =IFERROR((O44/M44-1),"") | U44: =IFERROR(F44/S44,"") | Y44: =IFERROR(F44/W44,"")
A45: Modal ditempatkan dan disetor | D45: 400000 | F45: ='Lap. PK - Kinerja Mei 2026'!E51 | I45: 400000 | K45: =IFERROR(F45/I45-1,"") | M45: 0 | O45: =F45-D45 | Q45: =IFERROR((O45/M45-1),"") | S45: 400000 | U45: =IFERROR(F45/S45,"") | W45: 400000 | Y45: =IFERROR(F45/W45,"") | AA45: 400000000000
A46: Cadangan umum | D46: 590498.33 | F46: ='Lap. PK - Kinerja Mei 2026'!E52 | I46: 476910 | K46: =IFERROR(F46/I46-1,"") | M46: 0 | O46: =F46-D46 | Q46: =IFERROR((O46/M46-1),"") | S46: 613705.51 | U46: =IFERROR(F46/S46,"") | W46: 754809.73 | Y46: =IFERROR(F46/W46,"") | AA46: 1.0703203e+11
A47: Laba (Rugi) Tahun Berjalan | D47: 51025.725 | F47: ='Lap. PK - Kinerja Mei 2026'!E53 | I47: 76784.855 | K47: =IFERROR(F47/I47-1,"") | M47: 20568.058 | O47: =F47-D47 | Q47: =IFERROR((O47/M47-1),"") | S47: 62049.835 | U47: =IFERROR(F47/S47,"") | W47: 151596.45 | Y47: =IFERROR(F47/W47,"") | AA47: 1.6317832e+10
A48: Saldo laba | D48: 163182.88 | F48: ='Lap. PK - Kinerja Mei 2026'!E54 | I48: 136795.51 | K48: =IFERROR(F48/I48-1,"") | M48: 9759.8024 | O48: =F48-D48 | Q48: =IFERROR((O48/M48-1),"") | S48: 141104.22 | U48: =IFERROR(F48/S48,"") | W48: 0 | Y48: =IFERROR(F48/W48,"") | AA48: 3.5942552e+11
A49: Deviden | D49: 0 | F49: 0 | I49: -1156.9619 | K49: =IFERROR(F49/I49-1,"") | M49: 0 | O49: =F49-D49 | Q49: =IFERROR((O49/M49-1),"") | S49: 0 | W49: -14110.422 | Y49: =IFERROR(F49/W49,"") | AA49: 0
A50: Komponen ekuitas lainnya | D50: -16440.473 | F50: ='Lap. PK - Kinerja Mei 2026'!E56 | I50: -15138.569 | K50: =IFERROR(F50/I50-1,"") | M50: -3481.4793 | O50: =F50-D50 | Q50: =IFERROR((O50/M50-1),"") | S50: 1309.7535 | U50: =IFERROR(F50/S50,"") | W50: 4089.3102 | Y50: =IFERROR(F50/W50,"") | AA50: -2.1564161e+09
G51: =SUM(G45:G50) | H51: =SUM(H45:H50)
G52: =G26+G43 | H52: =H26+H43

Sheet CASH FLOW Mei 2026
A1: Laporan Arus Kas Konsolidasi Askrindo dan Entitas Anak
A2: (dalam Jutaan Rupiah)
A3: KETERANGAN | B3: REALISASI 2025 (Audited) | C3: RKAP 2026 | D3: REALISASI SD APRIL 2026 | E3: REALISASI SD MEI 2026 | F3: REALISASI SD MEI 2025 | G3: RASIO (%)
G4: PENCAPAIAN THDP RKAP 2026 | H4: PERB. DNG. TAHUN 2025
A5: 1 | B5: 2 | C5: 3 | D5: 4 | E5: 5 | F5: 6 | G5: 7 = 5 : 3 | H5: 8 = (5-6) : 6
A6: Arus Kas dari Aktivitas Operasi
A7: Penerimaan Premi dan Jasa Penjaminan | B7: 836483.69 | C7: 901614.23 | D7: 324675.25 | E7: 402640.18 | F7: 285291.82 | G7: =IFERROR(E7/C7*100," ") | H7: =IFERROR((E7/F7-1)*100," ")
A8: Penerimaan Recoveries | B8: 83357.094 | C8: 59838.445 | D8: 19650.767 | E8: 23867.007 | F8: 40708.37 | G8: =IFERROR(E8/C8*100," ") | H8: =IFERROR((E8/F8-1)*100," ")
A9: Pembayaran Klaim | B9: -561199.63 | C9: -532402.64 | D9: -189063.43 | E9: -238716.92 | F9: -142376.86 | G9: =IFERROR(E9/C9*100," ") | H9: =IFERROR((E9/F9-1)*100," ")
A10: Penerimaan Klaim Reasuransi | B10: 160839.24 | C10: 172490.02 | D10: 44472.372 | E10: 54607.115 | F10: 52615.836 | G10: =IFERROR(E10/C10*100," ") | H10: =IFERROR((E10/F10-1)*100," ")
A11: Pembayaran Premi Reasuransi | B11: -158270.99 | C11: -179704.19 | D11: -38286.262 | E11: -55677.546 | F11: -53321.308 | G11: =IFERROR(E11/C11*100," ") | H11: =IFERROR((E11/F11-1)*100," ")
A12: Penerimaan Lainnya | B12: 963.56548 | C12: 1142.0298 | D12: 1147.748 | E12: 1587.2975 | F12: 265.85234 | G12: =IFERROR(E12/C12*100," ") | H12: =IFERROR((E12/F12-1)*100," ")
A13: Pembayaran Beban Pemasaran, Umum dan Adm. | B13: -121342.22 | C13: -145659.4 | D13: -56146.792 | E13: -67425.302 | F13: -54833.302 | G13: =IFERROR(E13/C13*100," ") | H13: =IFERROR((E13/F13-1)*100," ")
A14: Pembayaran Komisi | B14: -26407.318 | C14: -28444.964 | D14: -11179.315 | E14: -12851.728 | F14: -8005.3903 | G14: =IFERROR(E14/C14*100," ") | H14: =IFERROR((E14/F14-1)*100," ")
A15: Pembayaran Lainnya | B15: -64212.981 | C15: -60241.707 | D15: -24859.737 | E15: -30539.192 | F15: -21056.066 | G15: =IFERROR(E15/C15*100," ") | H15: =IFERROR((E15/F15-1)*100," ")
A16: Kas Bersih dihasilkan (dikeluarkan) dari aktivitas operasi | B16: 150210.45 | C16: 188631.81 | D16: 70410.606 | E16: 77490.908 | F16: 99288.948 | G16: =IFERROR(E16/C16*100," ") | H16: =IFERROR((E16/F16-1)*100," ")
G17: =IFERROR(E17/C17*100," ") | H17: =IFERROR((E17/F17-1)*100," ")
A18: Arus Kas dari Aktivitas Investasi | G18: =IFERROR(E18/C18*100," ") | H18: =IFERROR((E18/F18-1)*100," ")
A19: Penerimaan hasil investasi | B19: 151151.23 | C19: 157861.78 | D19: 43082.948 | E19: 55193.493 | F19: 58496.037 | G19: =IFERROR(E19/C19*100," ") | H19: =IFERROR((E19/F19-1)*100," ")
A20: Pencairan (Penempatan) Deposito | B20: -111800 | C20: -17000 | D20: 131300 | E20: 129050 | F20: -45250 | G20: =IFERROR(E20/C20*100," ") | H20: =IFERROR((E20/F20-1)*100," ")
A21: Pencairan (Penempatan) Surat Berharga | B21: -193855.21 | C21: -284426.46 | D21: -236813.1 | E21: -254940.4 | F21: -99051.486 | G21: =IFERROR(E21/C21*100," ") | H21: =IFERROR((E21/F21-1)*100," ")
A22: Hasil Penjualan Aset Tetap | C22: 0 | G22: =IFERROR(E22/C22*100," ") | H22: =IFERROR((E22/F22-1)*100," ")
A23: Perolehan Aset Tetap | B23: -2498.6573 | C23: -9541.148 | D23: -82.474778 | E23: -104.77478 | F23: -44.708493 | G23: =IFERROR(E23/C23*100," ") | H23: =IFERROR((E23/F23-1)*100," ")
A24: Penerimaan (Penempatan) Penyertaan Langsung | C24: 0 | G24: =IFERROR(E24/C24*100," ") | H24: =IFERROR((E24/F24-1)*100," ")
A25: Kas Bersih dihasilkan (dikeluarkan) dari aktivitas investasi | B25: -157002.64 | C25: -153105.83 | D25: -62512.626 | E25: -70801.683 | F25: -85850.157 | G25: =IFERROR(E25/C25*100," ") | H25: =IFERROR((E25/F25-1)*100," ")
G26: =IFERROR(E26/C26*100," ") | H26: =IFERROR((E26/F26-1)*100," ")
A27: Arus Kas dari Aktivitas Pendanaan | G27: =IFERROR(E27/C27*100," ") | H27: =IFERROR((E27/F27-1)*100," ")
A28: Penerimaan (Pembayaran) deviden | B28: -23207.172 | C28: -14110.422 | D28: 0 | E28: 0 | F28: 0 | G28: =IFERROR(E28/C28*100," ") | H28: =IFERROR((E28/F28-1)*100," ")
A29: Penerimaan atas Tambahan Modal disetor | B29: 0 | C29: 0 | D29: 0 | E29: 0 | F29: 0 | G29: =IFERROR(E29/C29*100," ") | H29: =IFERROR((E29/F29-1)*100," ")
A30: Penyaluran Dana Program Kemitraan dan Bina Lingkungan | C30: 0 | G30: =IFERROR(E30/C30*100," ") | H30: =IFERROR((E30/F30-1)*100," ")
A31: Kas Bersih dihasilkan (dikeluarkan) dari aktivitas pendanaan | B31: -23207.172 | C31: -14110.422 | D31: 0 | E31: 0 | F31: 0 | G31: =IFERROR(E31/C31*100," ") | H31: =IFERROR((E31/F31-1)*100," ")
C32: 0 | G32: =IFERROR(E32/C32*100," ") | H32: =IFERROR((E32/F32-1)*100," ")
A33: KENAIKAN/PENURUNAN SALDO KAS | B33: -29999.37 | C33: 21415.565 | D33: 7897.9801 | E33: 6689.2251 | F33: 13438.79 | G33: =IFERROR(E33/C33*100," ") | H33: =IFERROR((E33/F33-1)*100," ")
A34: Kas dan Setara Kas pada Awal Tahun | B34: 103869.27 | C34: 99508.07 | D34: 73869.903 | E34: 73869.903 | F34: 103869.27 | G34: =IFERROR(E34/C34*100," ") | H34: =IFERROR((E34/F34-1)*100," ")
G35: =IFERROR(E35/C35*100," ") | H35: =IFERROR((E35/F35-1)*100," ")
A36: Kas dan Setara Kas pada Akhir Tahun | B36: 73869.903 | C36: 120923.64 | D36: 81962.748 | E36: 80559.128 | F36: 117308.06 | G36: =IFERROR(E36/C36*100," ") | H36: =IFERROR((E36/F36-1)*100," ")

Sheet Hasil Underwriting
L1: Lampiran 1
A3: REALISASI HASIL UNDERWRITING
A4: PERIODE 1 JANUARI S/D 31 Mei 2026
A5: PT Jaminan Pembiayaan Askrindo Syariah
A6: (dalam jutaan rupiah)
A7: U R A I A N | B7: RKAP 2026 | C7: REALISASI s.d. Mei 2026 | D7: C L A S S O F B U S I N E S S | L7: % PENCAPAIAN THDP RKAP 2026
D8: Mikro | E8: Retail & Korporasi | F8: PEN | G8: KUR | H8: Konsumtif | I8: KBG | J8: Surety | K8: KPP
A10: 1 | B10: 2 | C10: 3 | D10: 4 | E10: 5 | F10: 6 | G10: 7 | H10: 8 | I10: 9 | J10: 10 | K10: 11 | L10: 12 = 3 : 2
A12: Pendapatan Premi
A13: Imbal Jasa Kafalah | B13: 9.037e+11 | C13: =SUM(D13:K13) | D13: ='Input HUW'!F4 | E13: ='Input HUW'!G4 | F13: ='Input HUW'!I4 | G13: ='Input HUW'!H4 | H13: ='Input HUW'!J4 | I13: ='Input HUW'!K4 | J13: ='Input HUW'!L4 | K13: ='Input HUW'!M4 | L13: =C13/B13
A14: Beban Penjaminan Ulang | B14: -2.3591461e+11 | C14: =SUM(D14:K14) | D14: ='Input HUW'!F6 | E14: ='Input HUW'!G6 | F14: ='Input HUW'!I6 | G14: ='Input HUW'!H6 | H14: ='Input HUW'!J6 | I14: ='Input HUW'!K6 | J14: ='Input HUW'!L6 | K14: ='Input HUW'!M6 | L14: =C14/B14
A15: Komisi penjaminan ulang | B15: 4.9076638e+10 | C15: =SUM(D15:K15) | D15: ='Input HUW'!F7+'Input HUW'!F8 | E15: ='Input HUW'!G7+'Input HUW'!G8 | F15: ='Input HUW'!I7+'Input HUW'!I8 | G15: ='Input HUW'!H7+'Input HUW'!H8 | H15: ='Input HUW'!J7+'Input HUW'!J8 | I15: ='Input HUW'!K7+'Input HUW'!K8 | J15: ='Input HUW'!L7+'Input HUW'!L8 | K15: ='Input HUW'!M7+'Input HUW'!M8 | L15: =C15/B15
A16: Penurunan (Kenaikan) Cad. Premi | B16: -9.1333788e+10 | C16: =SUM(D16:K16) | D16: ='Input HUW'!F9 | E16: ='Input HUW'!G9 | F16: ='Input HUW'!I9 | G16: ='Input HUW'!H9 | H16: ='Input HUW'!J9 | I16: ='Input HUW'!K9 | J16: ='Input HUW'!L9 | K16: ='Input HUW'!M9 | L16: =C16/B16
A17: Pendapatan Kafalah Lain | B17: 1.3610185e+08 | C17: =SUM(D17:K17) | D17: ='Input HUW'!F10 | E17: ='Input HUW'!G10 | F17: ='Input HUW'!I10 | G17: ='Input HUW'!H10 | H17: ='Input HUW'!J10 | I17: ='Input HUW'!K10 | J17: ='Input HUW'!L10 | K17: ='Input HUW'!M10 | L17: =C17/B17
A19: Jumlah Pendapatan Premi | B19: =SUM(B13:B18) | C19: =SUM(C13:C18) | D19: =SUM(D13:D18) | E19: =SUM(E13:E18) | F19: =SUM(F13:F18) | G19: =SUM(G13:G18) | H19: =SUM(H13:H18) | I19: =SUM(I13:I18) | ... K19: =SUM(K13:K18) | L19: =C19/B19
A21: Beban Underwriting
A22: Ta'widh Gross | B22: 5.3247327e+11 | C22: =SUM(D22:K22) | D22: ='Input HUW'!F13 | E22: ='Input HUW'!G13 | F22: ='Input HUW'!I13 | G22: ='Input HUW'!H13 | H22: ='Input HUW'!J13 | I22: ='Input HUW'!K13 | J22: ='Input HUW'!L13 | K22: ='Input HUW'!M13 | L22: =C22/B22
A23: Ta'widh Reas | B23: -1.7317154e+11 | C23: =SUM(D23:K23) | D23: ='Input HUW'!F14 | E23: ='Input HUW'!G14 | F23: ='Input HUW'!I14 | G23: ='Input HUW'!H14 | H23: ='Input HUW'!J14 | I23: ='Input HUW'!K14 | J23: ='Input HUW'!L14 | K23: ='Input HUW'!M14 | L23: =C23/B23
A24: Beban Komisi - bersih | B24: 2.578105e+10 | C24: =SUM(D24:K24) | D24: ='Input HUW'!F15+'Input HUW'!F16 | E24: ='Input HUW'!G15+'Input HUW'!G16 | F24: ='Input HUW'!I15+'Input HUW'!I16 | G24: ='Input HUW'!H15+'Input HUW'!H16 | H24: ='Input HUW'!J15+'Input HUW'!J16 | I24: ='Input HUW'!K15+'Input HUW'!K16 | J24: ='Input HUW'!L15+'Input HUW'!L16 | K24: ='Input HUW'!M15+'Input HUW'!M16 | L24: =C24/B24
A25: Pendapatan Recoveries - bersih | B25: -5.9838445e+10 | C25: =SUM(D25:K25) | D25: ='Input HUW'!F17 | E25: ='Input HUW'!G17 | F25: ='Input HUW'!I17 | G25: ='Input HUW'!H17 | H25: ='Input HUW'!J17 | I25: ='Input HUW'!K17 | J25: ='Input HUW'!L17 | K25: ='Input HUW'!M17 | L25: =C25/B25
A26: Kenaikan (Penurunan) Estimasi Ta'widh | B26: 7.0070686e+10 | C26: =SUM(D26:K26) | D26: ='Input HUW'!F18 | E26: ='Input HUW'!G18 | F26: ='Input HUW'!I18 | G26: ='Input HUW'!H18 | H26: ='Input HUW'!J18 | I26: ='Input HUW'!K18 | J26: ='Input HUW'!L18 | K26: ='Input HUW'!M18 | L26: =C26/B26
A27: Beban Underwriting Lain | B27: 3.2992045e+09 | C27: =SUM(D27:K27) | D27: ='Input HUW'!F19 | E27: ='Input HUW'!G19 | F27: ='Input HUW'!I19 | G27: ='Input HUW'!H19 | H27: ='Input HUW'!J19 | I27: ='Input HUW'!K19 | J27: ='Input HUW'!L19 | K27: ='Input HUW'!M19 | L27: =C27/B27
A29: Jumlah Beban Underwriting | B29: =SUM(B22:B27) | C29: =SUM(C22:C27) | D29: =SUM(D22:D27) | E29: =SUM(E22:E27) | F29: =SUM(F22:F27) | G29: =SUM(G22:G27) | H29: =SUM(H22:H27) | I29: =SUM(I22:I27) | ... K29: =SUM(K22:K27) | L29: =C29/B29
A31: Hasil Underwriting | B31: =B19-B29 | C31: =C19-C29 | D31: =D19-D29 | E31: =E19-E29 | F31: =F19-F29 | G31: =G19-G29 | H31: =H19-H29 | I31: =I19-I29 | ... K31: =K19-K29 | L31: =C31/B31

Sheet Input HUW
B2: INDIKATOR | C2: REALISASI JANUARI S/D FEBRUARI 2023 | D2: Realisasi sd Mei 2026 | P2: INDIKATOR
C3: TOTAL PRODUKTIF NON PROGRAM | D3: MIKRO PNM | E3: MIKRO NON PNM | F3: Mikro | G3: Retail & Korporasi | H3: KUR | I3: PEN | J3: Konsumtif | K3: KBG | L3: Surety | M3: KPP | N3: Total | Q3: Mikro | R3: Retail & Korporasi | S3: KUR | T3: PEN | U3: Konsumtif | V3: KBG | W3: Surety | X3: KPP | Y3: Total
B4: Imbal Jasa Kafalah Bruto | F4: 1.6576775e+11 | G4: 5.6527364e+09 | H4: 1.6506855e+11 | I4: 0 | J4: 1.9287765e+10 | K4: 3.2182935e+09 | L4: 35951042 | M4: 46044228200 | N4: =SUM(F4:M4) | P4: Imbal Jasa Kafalah Bruto | Q4: 1.4408064e+11 | R4: 4.8899243e+09 | S4: 1.2447017e+11 | T4: 0 | U4: 1.5789553e+10 | V4: 2.6711066e+09 | W4: 26577993 | X4: 36194650200 | Y4: 3.2812262e+11
N5: 0 | Q5: 0 | R5: 0 | S5: 0 | T5: 0 | U5: 0 | V5: 0 | W5: 0 | X5: 0 | Y5: 0
B6: Beban Penjaminan Ulang | F6: -4.1358321e+10 | G6: -2.2765399e+09 | H6: -4.0224766e+10 | I6: 0 | J6: -2.10899e+09 | K6: -1.3136673e+09 | L6: -9012760.6 | M6: -11511057050 | N6: =SUM(F6:M6) | P6: Beban Penjaminan Ulang | Q6: -3.5928577e+10 | R6: -2.0858369e+09 | S6: -2.9984358e+10 | T6: 0 | U6: -1.7473137e+09 | V6: -1.0957695e+09 | W6: -6669498.3 | X6: -9048662550 | Y6: -7.9897187e+10
B7: Komisi penjaminan ulang | F7: 1.0811279e+10 | G7: 5.0643409e+08 | H7: 9.9880431e+09 | I7: 0 | J7: 5.4517736e+08 | K7: 3.2328692e+08 | L7: 2393429 | M7: 2.8809769e+09 | N7: =SUM(F7:M7) | P7: Komisi penjaminan ulang | Q7: 9.4535139e+09 | R7: 4.5801231e+08 | S7: 7.3696048e+09 | T7: 0 | U7: 4.5486371e+08 | V7: 2.6880002e+08 | W7: 1802801.5 | X7: 2.2653783e+09 | Y7: 2.0271976e+10
B8: Komisi penjaminan ulang Tangguhan | F8: -5.3642607e+08 | G8: 8.5097398e+08 | H8: 4.5989555e+09 | I8: 0 | J8: 1.2940655e+09 | K8: -1.4972845e+08 | L8: 10342476 | M8: -2.6413733e+09 | N8: =SUM(F8:M8) | P8: Komisi penjaminan ulang Tangguhan | Q8: -1.492387e+09 | R8: 6.089964e+08 | S8: 4.1223826e+09 | T8: 0 | U8: 1.0005849e+09 | V8: -1.3945534e+08 | W8: 8196229.2 | X8: -2.1032777e+09 | Y8: 2.0050402e+09
B9: Penurunan (Kenaikan) IJK YBMP | F9: -2.9282313e+10 | G9: 1.5603493e+09 | H9: -5.3994189e+09 | I9: 0 | J9: -7.6386954e+08 | K9: -6.0221665e+08 | L9: 1.0740688e+08 | M9: -3.1725179e+10 | N9: =SUM(F9:M9) | P9: Penurunan (Kenaikan) IJK YBMP | Q9: -3.5056315e+10 | R9: 9.8684528e+08 | S9: -1.0023153e+09 | T9: 0 | U9: -1.5354459e+09 | V9: -5.9889895e+08 | W9: 85310561 | X9: -2.5258864e+10 | Y9: -6.2379684e+10
B10: Pendapatan Kafalah Lain | F10: 16219121 | G10: 553077.5 | H10: 16150709 | I10: 0 | J10: 1887161.9 | K10: 314885.68 | L10: 3517.5376 | M10: 4505079.5 | N10: =SUM(F10:M10) | P10: Pendapatan Kafalah Lain | Q10: 13809251 | R10: 468669.42 | S10: 11929706 | T10: 0 | U10: 1513332.3 | V10: 256009.28 | W10: 2547.3386 | X10: 3469036.5 | Y10: 31448552
B11: Jumlah Pendapatan Kafalah | F11: 1.0541819e+11 | G11: 6.294507e+09 | H11: 1.3404751e+11 | I11: 0 | J11: 1.8256035e+10 | K11: 1.4762829e+09 | L11: 1.4708459e+08 | M11: 3.0521012e+09 | N11: =SUM(F11:M11) | P11: Jumlah Pendapatan Kafalah | Q11: 5.7824621e+10 | R11: 3.5291298e+09 | S11: 7.7808854e+10 | T11: 0 | U11: 9.8654068e+09 | V11: 7.6601806e+08 | W11: 85792820 | X11: 9.5042416e+08 | Y11: 1.5083025e+11
N12: =SUM(F12:M12) | Y12: 0
B13: Ta'widh Bruto | F13: 1.2690423e+11 | G13: 1.5761998e+08 | H13: 9.9453924e+10 | I13: 0 | J13: 1.2032623e+10 | K13: 0 | L13: 0 | M13: 0 | N13: =SUM(F13:M13) | P13: Ta'widh Bruto | Q13: 1.0690095e+11 | R13: 36160438 | S13: 7.4115094e+10 | T13: 0 | U13: 7.9376334e+09 | V13: 0 | W13: 0 | X13: 0 | Y13: 1.8898984e+11
B14: Ta'widh Reas | F14: -3.3905391e+10 | G14: -59674768 | H14: -3.1887827e+10 | I14: 0 | J14: -1.0746723e+10 | K14: 0 | L14: 0 | M14: 0 | N14: =SUM(F14:M14) | P14: Ta'widh Reas | Q14: -2.8527555e+10 | R14: -29309883 | S14: -2.3778423e+10 | T14: 0 | U14: -7.9209565e+09 | V14: 0 | W14: 0 | X14: 0 | Y14: -6.0256244e+10
B15: Akuisisi | F15: 1.2566109e+10 | G15: 0 | H15: 0 | I15: 0 | J15: 15000 | K15: 2174094 | L15: 0 | M15: 0 | N15: =SUM(F15:M15) | P15: Akuisisi | Q15: 1.0930523e+10 | R15: 0 | S15: 0 | T15: 0 | U15: 15000 | V15: 2174094 | W15: 0 | X15: 0 | Y15: 1.0932712e+10
B16: Akuisisi Tangguhan | F16: -2.7315404e+09 | G16: 72275894 | H16: 0 | I16: 0 | J16: 1.2726199e+09 | K16: 5688569.4 | L16: 14385646 | M16: 0 | N16: =SUM(F16:M16) | P16: Akuisisi Tangguhan | Q16: -3.3748191e+09 | R16: 1.1539582e+08 | S16: -57575104 | T16: 0 | U16: 1.0180929e+09 | V16: 4116036.7 | W16: 11508517 | X16: 0 | Y16: -2.2832809e+09
B17: Recoveries | F17: -5.9371469e+09 | G17: -2.2887375e+08 | H17: -1.6706995e+10 | I17: -88327116 | J17: -9.0566424e+08 | K17: 0 | L17: 0 | M17: 0 | N17: =SUM(F17:M17) | P17: Recoveries | Q17: -4.8027085e+09 | R17: -2.0946552e+08 | S17: -1.3721323e+10 | T17: -71862239 | U17: -8.454077e+08 | V17: 0 | W17: 0 | X17: 0 | Y17: -1.9650767e+10
B18: Kenaikan (Penurunan) ETRS | F18: 4.4816992e+08 | G18: -4.5997038e+08 | H18: 2.0940458e+10 | I18: 0 | J18: -4.0745792e+09 | K18: 0 | L18: -1.1279677e+08 | M18: 0 | N18: =SUM(F18:M18) | P18: Kenaikan (Penurunan) ETRS | Q18: 3.3002966e+08 | R18: -6.4801849e+08 | S18: 2.6430628e+10 | T18: 0 | U18: -6.0313849e+09 | V18: 0 | W18: -1.1279677e+08 | X18: 0 | Y18: 1.9968458e+10
B19: Beban Kafalah Lain | F19: 4.4427874e+08 | G19: 551811.45 | H19: 3.4817803e+08 | I19: 0 | J19: 42124984 | K19: 0 | L19: 0 | M19: 0 | N19: =SUM(F19:M19) | P19: Beban Kafalah Lain | Q19: 3.9597357e+08 | R19: 133942.48 | S19: 2.7453094e+08 | T19: 0 | U19: 29401918 | V19: 0 | W19: 0 | X19: 0 | Y19: 7.0004037e+08
B20: Jumlah Beban Kafalah | F20: 9.7788706e+10 | G20: -5.1807122e+08 | H20: 7.2147737e+10 | I20: -88327116 | J20: -2.3795833e+09 | K20: 7862663.4 | L20: -98411122 | M20: 0 | N20: =SUM(F20:M20) | P20: Jumlah Beban Kafalah | Q20: 6.8819743e+10 | R20: -1.5728292e+09 | S20: 4.9180486e+10 | T20: -60988020 | U20: -5.4169623e+09 | V20: 4717598 | W20: -1.0416538e+08 | X20: 0 | Y20: 1.1085e+11
N21: =SUM(F21:M21) | Y21: =SUM(Q21:X21)
F22: 7.6294838e+09 | G22: 6.8125782e+09 | H22: 6.1899775e+10 | I22: 88327116 | J22: 2.0635618e+10 | K22: 1.4684203e+09 | L22: 2.4549571e+08 | M22: 3.0521012e+09 | N22: =SUM(F22:M22) | Q22: -1.0995122e+10 | R22: 5.101959e+09 | S22: 2.8628369e+10 | T22: 60988020 | U22: 1.5282369e+10 | V22: 7.6130047e+08 | W22: 1.899582e+08 | X22: 9.5042416e+08 | Y22: =SUM(Q22:X22)
B24: Hijau = sudah diupdate

Sheet Investasi Mei 2026
A2: LAPORAN KINERJA INVESTASI
A3: PER 31 Mei 2026
A4: PT. JAMINAN PEMBIAYAAN ASKRINDO SYARIAH
A6: Uraian | D6: RKAP 2026 | E6: Realisasi 2026 | H6: Realisasi 2025 | K6: Rasio (%)
E7: s.d. April 2026 | F7: Mei 2026 | G7: s.d. Mei 2026 | H7: s.d. April 2025 | I7: Mei 2025 | J7: s.d. Mei 2025 | K7: Pencapaian Terhadap RKAP 2026 | L7: Pertumbuhan Terhadap Bulan Yang Sama Tahun Lalu
A8: 1 | D8: 2 | E8: 3 | F8: 4=5-3 | G8: 5 | H8: 6 | I8: 7 = 8 -6 | J8: 8 | K8: 9 = 5 : 2 | L8: 10 = (5-8) : 8
A9: A. POSISI INVESTASI
B10: 1. | C10: Deposito | D10: 454400 | E10: 427450 | F10: 5100 | G10: 432550 | H10: 402200 | I10: 7850 | J10: 410050 | K10: 0.87400794 | L10: 0.054871357
C11: - Deposito yang dibatasi penggunaanya | D11: 100000 | E11: 50000 | F11: 0 | G11: 50000 | H11: 80000 | I11: 0 | J11: 80000 | K11: 0.5 | L11: -0.375
B12: 2. | C12: DOC | D12: 0 | E12: 4850 | F12: -2850 | G12: 2000 | H12: 90000 | I12: -33000 | J12: 57000 | K12: 0 | L12: -
B13: 3. | C13: Surat Berharga | D13: =SUM(D14:D16) | E13: 2017533.6 | F13: 13240.932 | G13: 2030774.6 | H13: 1669821 | I13: 47592.608 | J13: 1717413.6 | K13: 0.93305431 | L13: 0.18246099
C14: - Reksadana | D14: 142246.67 | E14: 100625.15 | F14: 10186.56 | G14: 110811.71 | H14: 90981.26 | I14: -10232.662 | J14: 80748.598 | K14: 0.77901093 | L14: 0.37230505
C15: -Saham | D15: 0 | E15: 0 | F15: 0 | G15: 0 | H15: 0 | I15: 0 | J15: 0 | K15: - | L15: -
C16: -Obligasi | D16: =D17+D18 | E16: 1916908.5 | F16: 3054.3717 | G16: 1919962.9 | H16: 1578839.7 | I16: 57825.27 | J16: 1636665 | K16: 0.94382601 | L16: 0.1730946
C17: Obligasi Pemerintah | D17: 1756273.9 | E17: 1893583.5 | F17: 3054.3717 | G17: 1896637.9 | H17: 1565839.7 | I17: 47825.27 | J17: 1613665 | K17: 1.0799215 | L17: 0.17536036
C18: Obligasi Korporasi | D18: 277960 | E18: 23325 | F18: 0 | G18: 23325 | H18: 13000 | I18: 10000 | J18: 23000 | K18: 0.083914952 | L18: 0.014130435
A19: TOTAL POSISI INVESTASI | D19: =D10+D11+D12+D13 | E19: 2499833.6 | F19: 15490.932 | G19: 2515324.6 | H19: 2242021 | I19: 22442.608 | J19: 2264463.6 | K19: 0.92106722 | L19: 0.11078164
A20: B. HASIL INVESTASI
B21: 1. | C21: Deposito | D21: 25260.5 | E21: 9178.2382 | F21: 1683.0568 | G21: 10861.295 | H21: 8956.7512 | I21: 2091.8582 | J21: 11048.609 | K21: 0.42997149 | L21: -0.016953673
B22: 2. | C22: DOC | D22: 0 | E22: 228.08757 | F22: 1.8083327 | G22: 229.8959 | H22: 50.495709 | I22: 69.377626 | J22: 119.87333 | K22: - | L22: -
B23: 3. | C23: Surat Berharga | D23: =SUM(D24:D26) | E23: 40756.013 | F23: 10709.131 | G23: 51465.144 | H23: 38095.145 | I23: 9938.749 | J23: 48033.893 | K23: 0.37803341 | L23: 0.071433946
C24: - Reksadana | D24: 7150.1572 | E24: 1103.4816 | F24: 225.05384 | G24: 1328.5354 | H24: 1762.9859 | I24: 679.07809 | J24: 2442.064 | K24: 0.18580507 | L24: -0.45597845
C25: -Saham | D25: 0 | E25: 0 | F25: 0 | G25: 0 | H25: 0 | I25: 0 | J25: 0 | K25: - | L25: -
C26: -Obligasi | D26: =D27+D28 | E26: 39652.531 | F26: 10484.077 | G26: 50136.609 | H26: 36332.159 | I26: 9259.6709 | J26: 45591.829 | K26: 0.38868907 | L26: 0.09968407
C27: Obligasi Pemerintah | D27: 118773.9 | E27: 38945.711 | F27: 10354.717 | G27: 49300.428 | H27: 36027.155 | I27: 9179.7264 | J27: 45206.882 | K27: 0.41507798 | L27: 0.090551401
C28: Obligasi Korporasi | D28: 10215.09 | E28: 706.82009 | F28: 129.36042 | G28: 836.18051 | H28: 305.00342 | I28: 79.944444 | J28: 384.94787 | K28: 0.081857381 | L28: 1.1721916
A29: TOTAL HASIL INVESTASI | D29: =D21+D22+D23 | E29: 50162.338 | F29: 12393.996 | G29: 62556.335 | H29: 47102.391 | I29: 12099.985 | J29: 59202.376 | K29: 0.38758658 | L29: 0.056652432
C31: Catatan :
B32: 1 | C32: Terdapat deposito yang dibatasi penggunaannya (restricted cash) sebesar Rp. 50 Miliar
B33: 2 | C33: Nilai tersebut (Rp. 50 Miliar) didalam neraca disajikan terpisah dengan investasi, namun pada kertas kerja ini
C34: kami tetap mengkategorikan sebagai instrumen deposito, mengingat dana tersebut secara prinsip merupakan
C35: deposito JPAS
B36: 3 | C36: Hasil Investasi disajikan secara Gross

Sheet List Deposito per Bank 
B1: RINGKASAN DATA DEPOSITO PER BANK (Mei 2026)
B2: NO | C2: NAMA BANK | D2: NOMINAL (Rp) | E2: JUMLAH BILYET
B3: 1 | C3: BANK SYARIAH INDONESIA | D3: 325850000000 | E3: 680
B4: 2 | C4: BANK SYARIAH NASIONAL | D4: 89500000000 | E4: 28
B5: 3 | C5: BANK PANIN DUBAI SYARIAH | D5: 17000000000 | E5: 7
B6: 4 | C6: BANK ACEH SYARIAH | D6: 12000000000 | E6: 6
B7: 5 | C7: BANK BPD JATENG SYARIAH | D7: 7000000000 | E7: 14
B8: 6 | C8: BANK BPR SYARIAH DINAR ASHRI | D8: 6000000000 | E8: 5
B9: 7 | C9: BANK BPD JATIM SYARIAH | D9: 5000000000 | E9: 2
B10: 8 | C10: BANK JABAR BANTEN SYARIAH | D10: 4000000000 | E10: 2
B11: 9 | C11: BANK SULSELBAR SYARIAH | D11: 3950000000 | E11: 5
B12: 10 | C12: BANK RIAU KEPRI SYARIAH | D12: 3650000000 | E12: 13
B13: 11 | C13: BANK SYARIAH BUKOPIN | D13: 3500000000 | E13: 6
B14: 12 | C14: BANK BTPN SYARIAH | D14: 2500000000 | E14: 1
... B19: 17 | C19: BANK BPD KALTIM KALTARA | D19: 100000000 | E19: 1
B20: TOTAL | D20: 484550000000 | E20: 775

Sheet Lap. LR-Kinerja Mei 2026
C1: PT JAMINAN PEMBIAYAAN ASKRINDO SYARIAH
C2: LAPORAN LABA RUGI KOMPREHENSIF
C3: Periode 1 Januari s.d 31 Mei 2026
G4: (Jutaan Rp)
C5: URAIAN | D5: Realisasi 1 Jan s.d 31 Des 2025 (Audited) | E5: Anggaran 1 Jan s.d 31 Des 2026 | F5: Realisasi s.d 31 Mei 2026 | G5: Rasio (%)
C7: 1 | D7: 2 | E7: 3 | F7: 4 | G7: 5 (4:3) | H7: 6 (4:2)
C8: PENDAPATAN KAFALAH
C9: Imbal jasa kafalah bruto | D9: 834065.23 | E9: 903700 | F9: 405075.27 | G9: =IFERROR((F9/E9)*100,"") | H9: =IFERROR((F9/D9)*100,"") | J9: Revenue
C10: Imbal jasa penjaminan ulang | D10: 0 | G10: =IFERROR((F10/E10)*100,"") | H10: =IFERROR((F10/D10)*100,"")
C11: Beban penjaminan ulang | D11: -220622.29 | E11: -235914.61 | F11: -98802.353 | G11: =IFERROR((F11/E11)*100,"") | H11: =IFERROR((F11/D11)*100,"") | J11: OpEx mirip dengan contra revenue
C12: Komisi penjaminan ulang | D12: 64844.141 | E12: 46976.345 | F12: 25057.591 | G12: =IFERROR((F12/E12)*100,"") | H12: =IFERROR((F12/D12)*100,"")
C13: Komisi penjaminan ulang tangguhan | D13: 6497.6313 | E13: 2100.2925 | F13: 3426.8096 | G13: =IFERROR((F13/E13)*100,"") | H13: =IFERROR((F13/D13)*100,"")
C14: Penurunan (Kenaikan) IJK YBMP | D14: -74516.128 | E14: -91333.788 | F14: -66105.241 | G14: =IFERROR((F14/E14)*100,"") | H14: =IFERROR((F14/D14)*100,"") | J14: Cadangan premi (unearned revenue)
C15: Penerimaan kafalah lain | D15: 127.52209 | E15: 136.10185 | F15: 39.633552 | G15: =IFERROR((F15/E15)*100,"") | H15: =IFERROR((F15/D15)*100,"")
C16: Jumlah Pendapatan Kafalah | D16: 610396.1 | E16: 625664.34 | F16: 268691.71 | G16: =IFERROR((F16/E16)*100,"") | H16: =IFERROR((F16/D16)*100,"") | J16: Net Revenue
G17: =IFERROR((F17/E17)*100,"") | H17: =IFERROR((F17/D17)*100,"")
C18: BEBAN KAFALAH | G18: =IFERROR((F18/E18)*100,"") | H18: =IFERROR((F18/D18)*100,"")
C19: Tawidh | D19: 561288.82 | E19: 532473.27 | F19: 238548.39 | G19: =IFERROR((F19/E19)*100,"") | H19: =IFERROR((F19/D19)*100,"") | J19: COGS
C20: Tawidh Reas | D20: -178340.37 | E20: -173171.54 | F20: -76599.616 | G20: =IFERROR((F20/E20)*100,"") | H20: =IFERROR((F20/D20)*100,"") | J20: (-) Purchase Returns & Allowances
C21: Beban akuisisi | D21: 25840.813 | E21: 29375 | F21: 12568.298 | G21: =IFERROR((F21/E21)*100,"") | H21: =IFERROR((F21/D21)*100,"") | J21: ?
C22: Beban akuisisi tangguhan | D22: -1348.2332 | E22: -3593.95 | F22: -1366.5704 | G22: =IFERROR((F22/E22)*100,"") | H22: =IFERROR((F22/D22)*100,"") | J22: ?
C23: Subrogasi | D23: -83357.094 | E23: -59838.445 | F23: -23867.007 | G23: =IFERROR((F23/E23)*100,"") | H23: =IFERROR((F23/D23)*100,"") | J23: recoveries
C24: Kenaikan (Penurunan) ETRS | D24: 76623.549 | E24: 70070.686 | F24: 16741.281 | G24: =IFERROR((F24/E24)*100,"") | H24: =IFERROR((F24/D24)*100,"") | J24: Bad Debt Expense
C25: Beban kafalah lain | D25: 2980.3344 | E25: 3299.2045 | F25: 835.13356 | G25: =IFERROR((F25/E25)*100,"") | H25: =IFERROR((F25/D25)*100,"")
C26: Jumlah Beban Kafalah | D26: 403687.82 | E26: 398614.22 | F26: 166859.91 | G26: =IFERROR((F26/E26)*100,"") | H26: =IFERROR((F26/D26)*100,"")
C27: Pendapatan Kafalah Bersih | D27: 206708.28 | E27: 227050.12 | F27: 101831.8 | G27: =IFERROR((F27/E27)*100,"") | H27: =IFERROR((F27/D27)*100,"") | J27: Gross Profit
G28: =IFERROR((F28/E28)*100,"") | H28: =IFERROR((F28/D28)*100,"")
C29: NISBAH (BAGI HASIL) INVESTASI | D29: 153658.39 | E29: 161399.64 | F29: 62556.335 | G29: =IFERROR((F29/E29)*100,"") | H29: =IFERROR((F29/D29)*100,"")
G30: =IFERROR((F30/E30)*100,"") | H30: =IFERROR((F30/D30)*100,"")
C31: BEBAN USAHA | G31: =IFERROR((F31/E31)*100,"") | H31: =IFERROR((F31/D31)*100,"") | J31: OpEX (SG&A)
C32: Beban Pemasaran | D32: 13136.563 | E32: 14704.226 | F32: 5562.0003 | G32: =IFERROR((F32/E32)*100,"") | H32: =IFERROR((F32/D32)*100,"")
C33: Beban Umum | D33: 99161.776 | E33: 120237.58 | F33: 44696.839 | G33: =IFERROR((F33/E33)*100,"") | H33: =IFERROR((F33/D33)*100,"")
C34: Beban Administrasi | D34: 20726.068 | E34: 24287.176 | F34: 7451.6472 | G34: =IFERROR((F34/E34)*100,"") | H34: =IFERROR((F34/D34)*100,"")
C35: Beban Penyusutan dan Amortisasi | D35: 14925.662 | E35: 17302.446 | F35: 5939.5001 | G35: =IFERROR((F35/E35)*100,"") | H35: =IFERROR((F35/D35)*100,"")
C36: Jumlah Beban Usaha | D36: 147950.07 | E36: 176531.42 | F36: 63649.986 | G36: =IFERROR((F36/E36)*100,"") | H36: =IFERROR((F36/D36)*100,"")
G37: =IFERROR((F37/E37)*100,"") | H37: =IFERROR((F37/D37)*100,"")
C38: LABA USAHA | D38: 212416.6 | E38: 211918.34 | F38: 100738.15 | G38: =IFERROR((F38/E38)*100,"") | H38: =IFERROR((F38/D38)*100,"")
E39: 0 | G39: =IFERROR((F39/E39)*100,"") | H39: =IFERROR((F39/D39)*100,"")
C40: PENDAPATAN (BEBAN) LAIN-LAIN | D40: -21683.627 | E40: -19963.356 | F40: -7929.3815 | G40: =IFERROR((F40/E40)*100,"") | H40: =IFERROR((F40/D40)*100,"")
G41: =IFERROR((F41/E41)*100,"") | H41: =IFERROR((F41/D41)*100,"")
C42: LABA SEBELUM ZAKAT | D42: 190732.98 | E42: 191954.98 | F42: 92808.767 | G42: =IFERROR((F42/E42)*100,"") | H42: =IFERROR((F42/D42)*100,"")
G43: =IFERROR((F43/E43)*100,"") | H43: =IFERROR((F43/D43)*100,"")
C44: Zakat | D44: 4768.3244 | E44: 4798.8746 | F44: 2320.2192 | G44: =IFERROR((F44/E44)*100,"") | H44: =IFERROR((F44/D44)*100,"")
G45: =IFERROR((F45/E45)*100,"") | H45: =IFERROR((F45/D45)*100,"")
C46: LABA SEBELUM PAJAK | D46: 185964.65 | E46: 187156.11 | F46: 90488.548 | G46: =IFERROR((F46/E46)*100,"") | H46: =IFERROR((F46/D46)*100,"")
G47: =IFERROR((F47/E47)*100,"") | H47: =IFERROR((F47/D47)*100,"")
C48: BEBAN (MANFAAT) PAJAK | G48: =IFERROR((F48/E48)*100,"") | H48: =IFERROR((F48/D48)*100,"")
C49: Pajak Tangguhan | D49: -8911.6417 | F49: 0 | G49: =IFERROR((F49/E49)*100,"") | H49: =IFERROR((F49/D49)*100,"")
C50: Pajak Kini | D50: 31693.418 | E50: 35559.661 | F50: 15777.49 | G50: =IFERROR((F50/E50)*100,"") | H50: =IFERROR((F50/D50)*100,"")
C51: Beban Pajak - Bersih | D51: 22781.776 | E51: 35559.661 | F51: 15777.49 | G51: =IFERROR((F51/E51)*100,"") | H51: =IFERROR((F51/D51)*100,"")
G52: =IFERROR((F52/E52)*100,"") | H52: =IFERROR((F52/D52)*100,"")
C53: LABA TAHUN BERJALAN | D53: 163182.88 | E53: 151596.45 | F53: 74711.058 | G53: =IFERROR((F53/E53)*100,"") | H53: =IFERROR((F53/D53)*100,"")
G54: =IFERROR((F54/E54)*100,"") | H54: =IFERROR((F54/D54)*100,"")
C55: PENGHASILAN (RUGI) KOMPREHENSIF LAIN | G55: =IFERROR((F55/E55)*100,"") | H55: =IFERROR((F55/D55)*100,"")
C56: Keuntungan/(Kerugian) Investasi AFS | D56: 31018.533 | E56: 2840.9601 | F56: -36357.956 | G56: =IFERROR((F56/E56)*100,"") | H56: =IFERROR((F56/D56)*100,"")
C57: Keuntungan/(Kerugian) Aktuaria bersih yang diakui | D57: -194.86544 | E57: 0 | F57: 0 | G57: =IFERROR((F57/E57)*100,"") | H57: =IFERROR((F57/D57)*100,"")
C58: PENGHASILAN (RUGI) KOMPREHENSIF LAIN - BERSIH | D58: 30823.667 | E58: 2840.9601 | F58: -36357.956 | G58: =IFERROR((F58/E58)*100,"") | H58: =IFERROR((F58/D58)*100,"")
C59: LABA KOMPREHENSIF | D59: 194006.54 | E59: 154437.41 | F59: 38353.102 | G59: =IFERROR((F59/E59)*100,"") | H59: =IFERROR((F59/D59)*100,"")

Sheet Lap. PK - Kinerja Mei 2026
B1: PT JAMINAN PEMBIAYAAN ASKRINDO SYARIAH
B2: LAPORAN POSISI KEUANGAN
B3: Per 31 Mei 2026
F4: (Jutaan Rp)
B5: URAIAN | C5: Realisasi per 31 Des 25 (Audited) | D5: Anggaran 2026 | E5: Realisasi per 31 Mei 2026 | F5: Rasio (%)
B7: 1 | C7: 2 | D7: 3 | E7: 4 | F7: 5 (4:3) | G7: 6 (4:2)
B9: ASET
B11: Kas dan bank | C11: 23869.903 | D11: 20924 | E11: 30559.128 | F11: 146.05076 | G11: 128.02368
B12: Deposito berjangka untuk tujuan tertentu | C12: 50000 | D12: 100000 | E12: 50000 | F12: 50 | G12: 100 | I12: Account Rec
B13: Piutang imbal jasa kafalah | C13: 3541.4689 | D13: 2960 | E13: 1967.8546 | F13: 66.48971 | G13: 55.566057 | I13: Allowance for doubtufull account
B14: Piutang imbal jasa kafalah - CKPN | C14: -1626.9139 | D14: - | E14: -1626.9139 | F14: 0 | G14: 100 | I14: receivable - claim recovery
B15: Piutang tawidh | C15: 61619.994 | D15: 56683 | E15: 83612.495 | F15: 147.50928 | G15: 135.69053
B16: Piutang tawidh - CKPN | C16: -899.86309 | D16: - | E16: -899.86309 | F16: 0 | G16: 100
B17: Piutang investasi | C17: 27279.873 | D17: 31921 | E17: 34642.715 | F17: 108.52525 | G17: 126.99001 | I17: Accrued interest
B18: Aset Reas | C18: 647000.06 | D18: 847155 | E18: 649442.41 | F18: 76.661553 | G18: 100.37749
B19: Biaya akuisisi yang ditangguhkan | C19: 36128.885 | D19: 37638 | E19: 37495.456 | F19: 99.620373 | G19: 103.78249 | I19: prepaid
B20: Biaya dibayar dimuka | C20: 829.737 | D20: 11889 | E20: 15767.556 | F20: 132.62599 | G20: 1900.3077 | I20: prepaid
B21: Pajak dibayar dimuka | C21: 1.9073486e-11 | D21: - | E21: 1.9073486e-11 | F21: 0 | G21: 100
B22: Investasi | F22: 0 | G22: 0
B23: Deposito | C23: 563600 | D23: 454400 | E23: 434550 | F23: 95.631602 | G23: 77.102555
B24: Reksadana | C24: 50557.501 | D24: 142247 | E24: 110811.71 | F24: 77.901093 | G24: 219.17956
B25: Surat Berharga Syariah Negara | C25: 1761634.6 | D25: 2034234 | E25: 1919962.9 | F25: 94.382601 | G25: 108.98758
B26: Aset pajak tangguhan | C26: 22839.203 | D26: 13873 | E26: 22839.203 | F26: 164.63536 | G26: 100 | I26: deferred tax
B27: Aset tetap | C27: 28516.272 | D27: 26434 | E27: 26367.793 | F27: 99.749663 | G27: 92.465778
B28: Aset tidak berwujud | C28: 2255.2848 | D28: 6638 | E28: 1846.8591 | F28: 27.824372 | G28: 81.890284
B29: Aset lain-lain | C29: 1859.6554 | D29: 3452 | E29: 1606.8143 | F29: 46.544745 | G29: 86.403873
F30: 0 | G30: 0
B31: JUMLAH ASET | C31: 3279005.7 | D31: 3790447 | E31: 3418946.1 | F31: 90.199027 | G31: 104.26777
F32: 0 | G32: 0
B33: LIABILITAS DAN EKUITAS | F33: 0 | G33: 0
F34: 0 | G34: 0
B35: Utang tawidh | C35: 213.8093 | D35: 2146 | E35: 45.282592 | F35: 2.1101507 | G35: 21.178963
B36: Utang penjaminan ulang | C36: 33327.255 | D36: 50513 | E36: 51394.471 | F36: 101.74542 | G36: 154.21153
B37: Utang Komisi | C37: 7948.4533 | D37: 9136 | E37: 7665.0231 | F37: 83.894887 | G37: 96.434146 | I37: accrued liabilities
B38: Pendapatan diterima dimuka | C38: 31210.445 | D38: 31937 | E38: 27201.735 | F38: 85.17255 | G38: 87.155871 | I38: unearned revenue
B39: Utang zakat | C39: 6303.2957 | D39: 7513 | E39: 5186.8036 | F39: 69.036098 | G39: 82.287169
B40: Utang pajak | C40: 10054.8 | D40: 18698 | E40: 13717.441 | F40: 73.362894 | G40: 136.42678
B41: Beban akrual | C41: 40672.599 | D41: 62693 | E41: 45895.602 | F41: 73.206413 | G41: 112.84158 | I41: Accrued Liabilities
B42: Estimasi tawidh retensi sendiri | C42: 437877.2 | D42: 657950 | E42: 459364.96 | F42: 69.817573 | G42: 104.90726 | I42: Allowance/claims reserve
B43: Estimasi IJK YBMP | C43: 1402018.4 | D43: 1502201 | E43: 1465819.5 | F43: 97.578103 | G43: 104.55066
B44: Pendapatan komisi yang ditangguhkan | C44: 130883.2 | D44: 140162 | E44: 127456.39 | F44: 90.935369 | G44: 97.38178
B45: Liabilitas imbalan kerja jangka panjang | C45: 246.29405 | D45: 134 | E45: 246.29405 | F45: 183.90204 | G45: 100
B46: Utang Deviden | C46: 0 | D46: - | E46: 0 | F46: 0 | G46: 0
B47: Utang lain-lain | C47: 9732.4595 | D47: 10978 | E47: 8081.9869 | F47: 73.623012 | G47: 83.041567
B48: Jumlah Liabilitas | C48: 2110488.2 | D48: 2494062 | E48: 2212075.5 | F48: 88.693697 | G48: 104.81345
F49: 0 | G49: 0
B50: EKUITAS | F50: 0 | G50: 0
B51: Modal ditempatkan dan disetor | C51: 400000 | D51: 400000 | E51: 400000 | F51: 100 | G51: 100
B52: Cadangan umum | C52: 590498.33 | D52: 754810 | E52: 590498.33 | F52: 78.231416 | G52: 100
B53: Laba (Rugi) Tahun Berjalan | C53: 163182.88 | D53: 151596 | E53: 74711.058 | F53: 49.282855 | G53: 45.783638
B54: Saldo laba | C54: -1.5258789e-11 | D54: - | E54: 163182.88 | F54: 0 | G54: 0
B55: Deviden | C55: 0 | D55: -14110 | E55: 0 | F55: 0 | G55: 0
B56: Komponen ekuitas lainnya | C56: 14836.247 | D56: 4089 | E56: -21521.709 | F56: -526.29192 | G56: -145.06168
B57: Jumlah Ekuitas | C57: 1168517.5 | D57: 1296385 | E57: 1206870.6 | F57: 93.095068 | G57: 103.2822
F58: 0 | G58: 0
B59: JUMLAH LIABILITAS DAN EKUITAS | C59: 3279005.7 | D59: 3790447 | E59: 3418946.1 | F59: 90.199027 | G59: 104.26777

Sheet Lap. AK-Kinerja Mei 2026
B2: PT JAMINAN PEMBIAYAAN ASKRINDO SYARIAH
B3: LAPORAN ARUS KAS
B4: Periode 1 Januari s.d 31 Mei 2026
F5: (Jutaan Rp)
B6: URAIAN | C6: Realisasi s.d 31 Des 2025 (Audited) | D6: Anggaran Tahun 2026 | E6: Realisasi s.d 31 Mei 2026 | F6: Rasio (%)
B8: 1 | C8: 2 | D8: 3 | E8: 4 | F8: 5 (4:3) | G8: 6 (4:2)
B10: A.Saldo Awal Bulan (Tahun) | C10: 103869.27 | D10: 99508 | E10: 73869.903 | F10: 74.235087 | G10: 71.118148
B12: B.Penerimaan
B13: 1.Penerimaan Pokok
B14: - Imbal jasa kafalah | C14: 836483.69 | D14: 901614 | E14: 402640.18 | F14: 44.6577 | G14: 48.134851
B15: - Recoveries | C15: 83357.094 | D15: 59838 | E15: 23867.007 | F15: 39.885741 | G15: 28.632245
B16: - Tawidh Reas | C16: 160839.24 | D16: 172490 | E16: 54607.115 | F16: 31.65813 | G16: 33.477876
F17: 0 | G17: 0
F18: 0 | G18: 0
B19: Jumlah | C19: 1080680 | D19: 1133943 | E19: 481114.3 | F19: 42.428449 | G19: 44.426073
F20: 0 | G20: 0
F21: 0 | G21: 0
B22: 2.Hasil Investasi | C22: 151151.23 | D22: 157862 | E22: 55193.493 | F22: 34.963176 | G22: 36.515411
B23: 3. Tambahan Modal Disetor | C23: 0 | D23: - | E23: 0 | F23: 0 | G23: 0
B24: 4. Penerimaan Kafalah Lain | C24: 127.52209 | D24: 136 | E24: 39.633552 | F24: 29.12051 | G24: 31.079755
B25: 5.Penerimaan Lain-Lain | C25: 836.04339 | D25: 1006 | E25: 1547.6639 | F25: 153.85435 | G25: 142.90244
F26: 0 | G26: 0
F27: 0 | G27: 0
B28: Jumlah Penerimaan | C28: 1232794.8 | D28: 1292947 | E28: 537895.09 | F28: 41.602269 | G28: 43.543096
F29: 0 | G29: 0
F30: 0 | G30: 0
F31: 0 | G31: 0
B32: C.Pengeluaran | F32: 0 | G32: 0
B33: 1. Beban Kafalah | F33: 0 | G33: 0
B34: - Ta'widh | C34: 561199.63 | D34: 532403 | E34: 238716.92 | F34: 44.837666 | G34: 42.536899
B35: - Biaya Akuisisi | C35: 26407.318 | D35: 28445 | E35: 12851.728 | F35: 45.181031 | G35: 48.667298
B36: - Beban Penjaminan Ulang | C36: 158270.99 | D36: 179704 | E36: 55677.546 | F36: 30.982886 | G36: 34.680166
B37: - Beban Kafalah lain | C37: 2980.3344 | D37: 3299 | E37: 835.13356 | F37: 25.31318 | G37: 28.021471
F38: 0 | G38: 0
F39: 0 | G39: 0
B40: Jumlah | C40: 748858.27 | D40: 743851 | E40: 308081.33 | F40: 41.417075 | G40: 41.015546
F41: 0 | G41: 0
F42: 0 | G42: 0
F43: 0 | G43: 0
B44: 2. Beban Usaha | F44: 0 | G44: 0
B45: - Pemasaran | C45: 13136.563 | D45: 14704 | E45: 5562.0003 | F45: 37.825863 | G45: 42.339845
B46: - Umum | C46: 87479.592 | D46: 106668 | E46: 54411.654 | F46: 51.010287 | G46: 63.552533
B47: - Administrasi | C47: 20726.068 | D47: 24287 | E47: 7451.6472 | F47: 30.681406 | G47: 35.456975
F48: 0 | G48: 0
F49: 0 | G49: 0
B50: Jumlah | C50: 121342.22 | D50: 145659 | E50: 67425.302 | F50: 46.2897 | G50: 56.295932
F51: 0 | G51: 0
F52: 0 | G52: 0
B53: 3. Beban Pajak | C53: 23851.571 | D53: 34326 | E53: 12114.85 | F53: 35.293175 | G53: 46.820644
B54: 4. Beban Zakat | C54: 6936.194 | D54: 5139 | E54: 3436.7113 | F54: 66.881082 | G54: 49.547508
B55: 5. Pengeluaran Lain-lain | C55: 30444.882 | D55: 17478 | E55: 14152.497 | F55: 80.974888 | G55: 46.435959
B56: 6. Belanja Modal | C56: 2498.6573 | D56: 9541 | E56: 104.77478 | F56: 1.098136 | G56: 4.2638106
B57: 7.Pembayaran Deviden | C57: 23207.172 | D57: 14110 | E57: 0 | F57: 0 | G57: 0
F58: 0 | G58: 0
B59: Jumlah Pengeluaran (C) | C59: 957138.97 | D59: 970104 | E59: 405315.46 | F59: 41.780599 | G59: 42.226712
F60: 0 | G60: 0
F61: 0 | G61: 0
B62: Surplus (Defisit) Dana (B-C) | C62: 275655.84 | D62: 322842 | E62: 132579.63 | F62: 41.066409 | G62: 48.130093
F63: 0 | G63: 0
F64: 0 | G64: 0
B65: D. Penambahan (Pencairan) Investasi | C65: 305655.21 | D65: 301426 | E65: 125890.4 | F65: 41.764944 | G65: 41.213336
F66: 0 | G66: 0
F67: 0 | G67: 0
B68: Saldo Akhir (A+B-C-D) | C68: 73869.903 | D68: 120924 | E68: 80559.128 | F68: 66.619582 | G68: 109.05541
F69: 0 | G69: 0
B70: Saldo Akhir terdiri dari | F70: 0 | G70: 0
B71: Kas dan bank | C71: 23869.903 | D71: 20924 | E71: 30559.128 | F71: 146.05076 | G71: 128.02368
B72: Kas yang dibatasi | C72: 50000 | D72: 100000 | E72: 50000 | F72: 50 | G72: 100

Sheet Beban Usaha
G1: Dalam Juta Rupiah
B2: K E T E R A N G A N | G2: Realisasi s.d Mei 25 | H2: Realisasi s.d Des 25 (Audited) | I2: RKAP 2026 | J2: Realisasi s.d April 26 | K2: Mutasi Mei 26 | L2: Realisasi s.d Mei 26 | M2: Rasio (%)
B3: 1 | G3: 2 (INPUT) | H3: 3 | I3: 4 | J3: 5 (INPUT) | K3: 6 | L3: 7 (INPUT) | M3: 8 (7/4) | N3: 9 (7/2)
B4: A. | C4: BEBAN PEMASARAN | G4: 4712.1651 | H4: 13136.563 | I4: 14704.226 | J4: 4349.7301 | K4: =L4-J4 | L4: 5562.0003 | M4: =IF(I4=0,0,$K4/I4*100) | N4: =IF(G4=0,0,$K4/G4*100)
B5: B. | C5: BEBAN UMUM | G5: 39671.097 | H5: 99161.776 | I5: 120237.58 | J5: 34312.458 | K5: =L5-J5 | L5: 44696.839 | M5: =IF(I5=0,0,$K5/I5*100) | N5: =IF(G5=0,0,$K5/G5*100)
B6: C. | C6: BEBAN ADMINISTRASI | G6: 7210.0197 | H6: 20726.068 | I6: 24287.176 | J6: 5846.7861 | K6: =L6-J6 | L6: 7451.6472 | M6: =IF(I6=0,0,$K6/I6*100) | N6: =IF(G6=0,0,$K6/G6*100)
B7: D. | C7: BEBAN PENYUSUTAN DAN AMORTISASI | G7: 6389.3085 | H7: 14925.662 | I7: 17302.446 | J7: 4728.0455 | K7: =L7-J7 | L7: 5939.5001 | M7: =IF(I7=0,0,$K7/I7*100) | N7: =IF(G7=0,0,$K7/G7*100)
B8: J U M L A H | G8: 57982.591 | H8: 147950.07 | I8: 176531.42 | J8: 49237.019 | K8: =L8-J8 | L8: 63649.986 | M8: =IF(I8=0,0,$K8/I8*100) | N8: =IF(G8=0,0,$K8/G8*100)
B10: A. | C10: BEBAN PEMASARAN
C12: 1. | D12: P R O M O S I | G12: 228.32 | H12: 1111.8233 | I12: 1058.7285 | J12: 202.05 | K12: =L12-J12 | L12: 262.05 | M12: =IF(I12=0,0,$K12/I12*100) | N12: =IF(G12=0,0,$K12/G12*100)
C13: 2. | D13: PERJALANAN DINAS | G13: 0 | H13: 0 | I13: 0 | J13: 0 | K13: =L13-J13 | L13: 0 | M13: =IF(I13=0,0,$K13/I13*100) | N13: =IF(G13=0,0,$K13/G13*100)
C14: 3. | D14: BEBAN RAPAT | G14: 101.68257 | H14: 387.79836 | I14: 1709.617 | J14: 79.005393 | K14: =L14-J14 | L14: 324.49264 | M14: =IF(I14=0,0,$K14/I14*100) | N14: =IF(G14=0,0,$K14/G14*100)
C15: 4. | D15: ENTERTAINMENT DAN REPRESENTASI | G15: 3769.4746 | H15: 10610.822 | I15: 10318.417 | J15: 3875.0516 | K15: =L15-J15 | L15: 4718.3219 | M15: =IF(I15=0,0,$K15/I15*100) | N15: =IF(G15=0,0,$K15/G15*100)
C16: 5. | D16: MERCHANDISE | G16: 12 | H16: 42.127762 | I16: 123.23834 | J16: 0 | K16: =L16-J16 | L16: 0 | M16: =IF(I16=0,0,$K16/I16*100) | N16: =IF(G16=0,0,$K16/G16*100)
C17: 6. | D17: RAKER | G17: 389.22631 | H17: 689.83891 | I17: 1035.2811 | J17: 187.12309 | K17: =L17-J17 | L17: 250.63574 | M17: =IF(I17=0,0,$K17/I17*100) | N17: =IF(G17=0,0,$K17/G17*100)
C18: 7. | D18: REWARD ACHIVEMENT | G18: 211.4616 | H18: 294.15194 | I18: 458.94402 | J18: 6.5 | K18: =L18-J18 | L18: 6.5 | M18: =IF(I18=0,0,$K18/I18*100) | N18: =IF(G18=0,0,$K18/G18*100)
B20: TOTAL A : BEBAN PEMASARAN | G20: 4712.1651 | H20: 13136.563 | I20: 14704.226 | J20: 4349.7301 | K20: =L20-J20 | L20: 5562.0003 | M20: =IF(I20=0,0,$K20/I20*100) | N20: =IF(G20=0,0,$K20/G20*100)
B22: B. | C22: BEBAN UMUM
C23: 1. | D23: BEBAN PEGAWAI
D24: 1.1. | E24: Gaji/Honor Dewan Pengawas Syariah | G24: 117.42 | H24: 316.32 | I24: 409.032 | J24: 102.6 | K24: =L24-J24 | L24: 136.8 | M24: =IF(I24=0,0,$K24/I24*100) | N24: =IF(G24=0,0,$K24/G24*100)
D25: 1.2. | E25: Gaji/Honor Dewan Komisaris | G25: 1123.9405 | H25: 2894.3362 | I25: 3304 | J25: 922.66192 | K25: =L25-J25 | L25: 1201.5619 | M25: =IF(I25=0,0,$K25/I25*100) | N25: =IF(G25=0,0,$K25/G25*100)
D26: 1.3. | E26: Take Home Pay Direksi | G26: 1720.406 | H26: 4631.5926 | I26: 4932.72 | J26: 1426.477 | K26: =L26-J26 | L26: 1850.777 | M26: =IF(I26=0,0,$K26/I26*100) | N26: =IF(G26=0,0,$K26/G26*100)
D27: 1.4. | E27: Gaji Pegawai | G27: 13421.734 | H27: 34555.545 | I27: 37922.72 | J27: 11458.961 | K27: =L27-J27 | L27: 14665.461 | M27: =IF(I27=0,0,$K27/I27*100) | N27: =IF(G27=0,0,$K27/G27*100)
D28: 1.5. | E28: Honor Outsourcing | G28: 2488.1728 | H28: 7022.576 | I28: 5244.4213 | J28: 2377.7073 | K28: =L28-J28 | L28: 3019.3502 | M28: =IF(I28=0,0,$K28/I28*100) | N28: =IF(G28=0,0,$K28/G28*100)
D29: 1.6. | E29: L e m b u r | G29: 59.254864 | H29: 132.21304 | I29: 101.29585 | J29: 16.215046 | K29: =L29-J29 | L29: 20.295401 | M29: =IF(I29=0,0,$K29/I29*100) | N29: =IF(G29=0,0,$K29/G29*100)
D30: 1.7. | E30: Tunjangan - Tunjangan
E31: 1.7.1. | F31: Hari Raya | G31: 2616.3702 | H31: 6382.4406 | I31: 6829.21 | J31: 2215.6025 | K31: =L31-J31 | L31: 2784.7033 | M31: =IF(I31=0,0,$K31/I31*100) | N31: =IF(G31=0,0,$K31/G31*100)
E32: 1.7.2. | F32: Bantuan Pendidikan | G32: 1145.11 | H32: 2864.4599 | I32: 2796.8036 | J32: 932.26785 | K32: =L32-J32 | L32: 1165.3348 | M32: =IF(I32=0,0,$K32/I32*100) | N32: =IF(G32=0,0,$K32/G32*100)
E33: 1.7.3. | F33: Bantuan Qurban | G33: 0 | H33: 0 | J33: 0 | K33: =L33-J33 | L33: 0 | M33: =IF(I33=0,0,$K33/I33*100) | N33: =IF(G33=0,0,$K33/G33*100)
E34: 1.7.4. | F34: Zakat Pegawai | G34: 0 | H34: 0 | J34: 0 | K34: =L34-J34 | L34: 0 | M34: =IF(I34=0,0,$K34/I34*100) | N34: =IF(G34=0,0,$K34/G34*100)
E35: 1.7.5. | F35: Pajak Pasal 21 | G35: 2924.6343 | H35: 7483.0684 | I35: 10212.807 | J35: 1454.7054 | K35: =L35-J35 | L35: 2420.0054 | M35: =IF(I35=0,0,$K35/I35*100) | N35: =IF(G35=0,0,$K35/G35*100)
E36: 1.7.6. | F36: Cuti | G36: 1739.6598 | H36: 3121.8632 | I36: 3665.8629 | J36: 1637.0125 | K36: =L36-J36 | L36: 1958.3042 | M36: =IF(I36=0,0,$K36/I36*100) | N36: =IF(G36=0,0,$K36/G36*100)
E37: Sub Jumlah Tunjangan-Tunjangan | G37: 8425.7742 | H37: 19851.832 | I37: 23504.683 | J37: 6239.5883 | K37: =L37-J37 | L37: 8328.3477 | M37: =IF(I37=0,0,$K37/I37*100) | N37: =IF(G37=0,0,$K37/G37*100)
D39: 1.8. | E39: Kesejahteraan Pegawai
E40: 1.8.1. | F40: Premi Asuransi Pensiun & THT | G40: 1815.5925 | H40: 1765.0926 | I40: 4167.9761 | J40: 917.00039 | K40: =L40-J40 | L40: 1298.2004 | M40: =IF(I40=0,0,$K40/I40*100) | N40: =IF(G40=0,0,$K40/G40*100)
E41: 1.8.2. | F41: J a m s o s t e k | G41: 785.96092 | H41: 1877.0307 | I41: 2299.2233 | J41: 868.59106 | K41: =L41-J41 | L41: 1117.5911 | M41: =IF(I41=0,0,$K41/I41*100) | N41: =IF(G41=0,0,$K41/G41*100)
E42: 1.8.3. | F42: Bantun Awal Tahun | G42: 959.83467 | H42: 2742.2985 | I42: 2796.8036 | J42: 822.64235 | K42: =L42-J42 | L42: 1029.8299 | M42: =IF(I42=0,0,$K42/I42*100) | N42: =IF(G42=0,0,$K42/G42*100)
E43: 1.8.4 | F43: Bantuan Tri Wulan | G43: 640.99971 | H43: 1538.3991 | I43: 3160.23 | J43: 1053.41 | K43: =L43-J43 | L43: 1316.7625 | M43: =IF(I43=0,0,$K43/I43*100) | N43: =IF(G43=0,0,$K43/G43*100)
E44: 1.8.5. | F44: Pakaian Kerja | G44: 11.1 | H44: 147.948 | I44: 200 | J44: 6.58674 | K44: =L44-J44 | L44: 6.58674 | M44: =IF(I44=0,0,$K44/I44*100) | N44: =IF(G44=0,0,$K44/G44*100)
E45: 1.8.4. | F45: Pengobatan / Rumah Sakit | G45: 1569.7518 | H45: 3816.2557 | I45: 4866.1369 | J45: 1759.0914 | K45: =L45-J45 | L45: 2147.8309 | M45: =IF(I45=0,0,$K45/I45*100) | N45: =IF(G45=0,0,$K45/G45*100)
E46: 1.8.6. | F46: Bantuan Kacamata | G46: 120.9905 | H46: 229.9617 | I46: 256.45714 | J46: 161.732 | K46: =L46-J46 | L46: 173.482 | M46: =IF(I46=0,0,$K46/I46*100) | N46: =IF(G46=0,0,$K46/G46*100)
E47: Sub Jumlah beban Kesejahteraan Pegawai | G47: 5904.2302 | H47: 12116.986 | I47: 17746.827 | J47: 5589.0539 | K47: =L47-J47 | L47: 7090.2835 | M47: =IF(I47=0,0,$K47/I47*100) | N47: =IF(G47=0,0,$K47/G47*100)
D49: 1.9. | E49: Beban Penerimaan dan Seleksi Pegawai | G49: 32.1345 | H49: 217.1985 | I49: 222.2 | J49: 15.73075 | K49: =L49-J49 | L49: 41.87125 | M49: =IF(I49=0,0,$K49/I49*100) | N49: =IF(G49=0,0,$K49/G49*100)
D50: 1.10. | E50: Beban Jasa Produksi | G50: 1386.7098 | H50: 3328.1119 | I50: 6320.4534 | J50: 2106.8178 | K50: =L50-J50 | L50: 2633.5222 | M50: =IF(I50=0,0,$K50/I50*100) | N50: =IF(G50=0,0,$K50/G50*100)
D51: 1.11. | E51: Beban Tantiem | G51: 1596.232 | H51: 3830.9415 | I51: 4214.0406 | J51: 1404.6802 | K51: =L51-J51 | L51: 1755.8503 | M51: =IF(I51=0,0,$K51/I51*100) | N51: =IF(G51=0,0,$K51/G51*100)
D53: JUMLAH BEBAN PEGAWAI | G53: 36276.009 | H53: 88897.653 | I53: 103922.39 | J53: 31660.493 | K53: =L53-J53 | L53: 40744.12 | M53: =IF(I53=0,0,$K53/I53*100) | N53: =IF(G53=0,0,$K53/G53*100)
C55: 2. | D55: BEBAN PERJALANAN DINAS | G55: 830.34819 | H55: 3046.1953 | I55: 2482.4293 | J55: 343.14497 | K55: =L55-J55 | L55: 586.0947 | M55: =IF(I55=0,0,$K55/I55*100) | N55: =IF(G55=0,0,$K55/G55*100)
C56: 3. | D56: BEBAN PENDIDIKAN DAN LATIHAN | G56: 311.26308 | H56: 1647.7031 | I56: 3195.1681 | J56: 429.47291 | K56: =L56-J56 | L56: 711.01203 | M56: =IF(I56=0,0,$K56/I56*100) | N56: =IF(G56=0,0,$K56/G56*100)
C57: 4. | D57: IURAN KEANGGOTAAN | G57: 649.31796 | H57: 1725.1932 | I57: 2193.0702 | J57: 461.49002 | K57: =L57-J57 | L57: 885.717 | M57: =IF(I57=0,0,$K57/I57*100) | N57: =IF(G57=0,0,$K57/G57*100)
C58: 5. | D58: BEBAN UMUM LAINNYA
D59: 5.1 | E59: Beban Rapat Kerja | K59: =L59-J59
D60: 5.2 | E60: Beban Rapat Pemegang Saham | G60: 0 | H60: 0 | J60: 0 | K60: =L60-J60 | L60: 0 | M60: =IF(I60=0,0,$K60/I60*100) | N60: =IF(G60=0,0,$K60/G60*100)
D61: 5.3 | E61: Jamuan Rapat | G61: 119.39497 | H61: 265.69286 | I61: 331.71429 | J61: 13.698353 | K61: =L61-J61 | L61: 16.005378 | M61: =IF(I61=0,0,$K61/I61*100) | N61: =IF(G61=0,0,$K61/G61*100)
D62: 5.4 | E62: Beban Pindah/ Beban Detasering | G62: 264.046 | H62: 510.00603 | I62: 712.8 | J62: 288.26146 | K62: =L62-J62 | L62: 299.76885 | M62: =IF(I62=0,0,$K62/I62*100) | N62: =IF(G62=0,0,$K62/G62*100)
D63: Sub Jumlah Beban Umum Lainnya | G63: 383.44097 | H63: 775.69889 | I63: 1044.5143 | J63: 301.95981 | K63: =L63-J63 | L63: 315.77423 | M63: =IF(I63=0,0,$K63/I63*100) | N63: =IF(G63=0,0,$K63/G63*100)
C64: 6. | D64: BEBAN KONSULTAN | G64: 1220.7183 | H64: 3069.3323 | I64: 7400 | J64: 1115.8969 | K64: =L64-J64 | L64: 1454.1204 | M64: =IF(I64=0,0,$K64/I64*100) | N64: =IF(G64=0,0,$K64/G64*100)
C66: TOTAL B : BEBAN UMUM | G66: 39671.097 | H66: 99161.776 | I66: 120237.58 | J66: 34312.458 | K66: =L66-J66 | L66: 44696.839 | M66: =IF(I66=0,0,$K66/I66*100) | N66: =IF(G66=0,0,$K66/G66*100)
B68: C. | C68: BEBAN ADMINISTRASI
C69: 1. | D69: BEBAN PERKANTORAN
D70: 1.1. | E70: S e w a - Gedung kantor | G70: 13.815024 | H70: 95.006452 | I70: 158.4 | J70: 386.49015 | K70: =L70-J70 | L70: 390.01015 | M70: =IF(I70=0,0,$K70/I70*100) | N70: =IF(G70=0,0,$K70/G70*100)
D71: 1.2. | E71: Listrik dan Air - Gedung Kantor | G71: 162.96888 | H71: 407.44034 | I71: 428.05714 | J71: 126.91406 | K71: =L71-J71 | L71: 155.1407 | M71: =IF(I71=0,0,$K71/I71*100) | N71: =IF(G71=0,0,$K71/G71*100)
D72: 1.3. | E72: Perawatan - Gedung Kantor | G72: 228.16495 | H72: 547.95986 | I72: 493.14012 | J72: 223.57158 | K72: =L72-J72 | L72: 266.91982 | M72: =IF(I72=0,0,$K72/I72*100) | N72: =IF(G72=0,0,$K72/G72*100)
D73: 1.6. | E73: Beban Pindah - Gedung Kantor | G73: 4.5 | H73: 4.5 | I73: 150 | J73: 0 | K73: =L73-J73 | L73: 0 | M73: =IF(I73=0,0,$K73/I73*100) | N73: =IF(G73=0,0,$K73/G73*100)
D74: 1.7. | E74: Gas dan Diesel - Gedung Kantor | G74: 0 | H74: 0 | J74: 0 | K74: =L74-J74 | L74: 0 | M74: =IF(I74=0,0,$K74/I74*100) | N74: =IF(G74=0,0,$K74/G74*100)
D75: JUMLAH BEBAN PERKANTORAN | G75: 409.44886 | H75: 1054.9066 | I75: 1229.5973 | J75: 736.97578 | K75: =L75-J75 | L75: 812.07066 | M75: =IF(I75=0,0,$K75/I75*100) | N75: =IF(G75=0,0,$K75/G75*100)
C77: 2. | D77: BEBAN PERUMAHAN
D78: 2.1. | E78: S e w a - Rumah Dinas | G78: 778.10714 | H78: 2013.2883 | I78: 1878.8156 | J78: 583.09444 | K78: =L78-J78 | L78: 747.49444 | M78: =IF(I78=0,0,$K78/I78*100) | N78: =IF(G78=0,0,$K78/G78*100)
D79: 2.2 | E79: Listrik dan Air - Rumah Dinas | G79: 0 | H79: 0 | J79: 0 | K79: =L79-J79 | L79: 0 | M79: =IF(I79=0,0,$K79/I79*100) | N79: =IF(G79=0,0,$K79/G79*100)
D80: 2.3. | E80: Gas dan Diesel - Rumah Dinas | G80: 0 | H80: 0 | J80: 0 | K80: =L80-J80 | L80: 0 | M80: =IF(I80=0,0,$K80/I80*100) | N80: =IF(G80=0,0,$K80/G80*100)
D81: JUMLAH BEBAN PERUMAHAN | G81: 778.10714 | H81: 2013.2883 | I81: 1878.8156 | J81: 583.09444 | K81: =L81-J81 | L81: 747.49444 | M81: =IF(I81=0,0,$K81/I81*100) | N81: =IF(G81=0,0,$K81/G81*100)
C83: 3. | D83: BEBAN KANTOR
D84: 3.1. | E84: Beban Peralatan Kantor
E85: 3.1.1. | F85: Alat Tulis Kantor | G85: 66.118707 | H85: 148.08009 | I85: 498.77143 | J85: 58.097513 | K85: =L85-J85 | L85: 94.300719 | M85: =IF(I85=0,0,$K85/I85*100) | N85: =IF(G85=0,0,$K85/G85*100)
E86: 3.1.2. | F86: Barang Cetakan | G86: 54.367432 | H86: 216.13037 | I86: 550 | J86: 20.508955 | K86: =L86-J86 | L86: 22.02556 | M86: =IF(I86=0,0,$K86/I86*100) | N86: =IF(G86=0,0,$K86/G86*100)
E87: 3.1.3. | F87: M a t e r a i | G87: 5.6615 | H87: 26.2637 | I87: 20.742857 | J87: 13.7685 | K87: =L87-J87 | L87: 14.8865 | M87: =IF(I87=0,0,$K87/I87*100) | N87: =IF(G87=0,0,$K87/G87*100)
E88: 3.1.4. | F88: Foto Copy | G88: 125.28362 | H88: 327.8231 | I88: 6 | J88: 129.52033 | K88: =L88-J88 | L88: 129.52033 | M88: =IF(I88=0,0,$K88/I88*100) | N88: =IF(G88=0,0,$K88/G88*100)
E89: 3.1.5. | F89: D o k u m e n t a s i | G89: 0 | H89: 0 | J89: 0 | K89: =L89-J89 | L89: 0 | M89: =IF(I89=0,0,$K89/I89*100) | N89: =IF(G89=0,0,$K89/G89*100)
E90: 3.1.6. | F90: Keperluan Dapur | G90: 131.86749 | H90: 348.49978 | I90: 375 | J90: 120.51345 | K90: =L90-J90 | L90: 151.94048 | M90: =IF(I90=0,0,$K90/I90*100) | N90: =IF(G90=0,0,$K90/G90*100)
E91: 3.1.7. | F91: Supplies Mesin Kantor | G91: 3.768116 | H91: 9.756961 | I91: 60 | J91: 0.3835 | K91: =L91-J91 | L91: 0.6782 | M91: =IF(I91=0,0,$K91/I91*100) | N91: =IF(G91=0,0,$K91/G91*100)
E92: 3.1.8. | F92: Inventaris Kecil | G92: 68.452877 | H92: 160.80085 | I92: 150.85714 | J92: 41.412544 | K92: =L92-J92 | L92: 52.381867 | M92: =IF(I92=0,0,$K92/I92*100) | N92: =IF(G92=0,0,$K92/G92*100)
E93: 3.1.9. | F93: Kearsipan | G93: 0 | H93: 0 | J93: 0 | K93: =L93-J93 | L93: 0 | M93: =IF(I93=0,0,$K93/I93*100) | N93: =IF(G93=0,0,$K93/G93*100)
E94: Sub Jumlah | G94: 455.51975 | H94: 1237.3549 | I94: 1661.3714 | J94: 384.2048 | K94: =L94-J94 | L94: 465.73365 | M94: =IF(I94=0,0,$K94/I94*100) | N94: =IF(G94=0,0,$K94/G94*100)
D96: 3.2. | E96: Beban Kantor Lainnya
E97: 3.2.1. | F97: Sumbangan Sosial | G97: 280.67071 | H97: 945.99993 | I97: 946 | J97: 159.54096 | K97: =L97-J97 | L97: 175.09096 | M97: =IF(I97=0,0,$K97/I97*100) | N97: =IF(G97=0,0,$K97/G97*100)
E98: 3.2.2. | F98: Retribusi Kebersihan dan Keamanan | G98: 28.26375 | H98: 64.3368 | I98: 73.542857 | J98: 19.43706 | K98: =L98-J98 | L98: 22.71206 | M98: =IF(I98=0,0,$K98/I98*100) | N98: =IF(G98=0,0,$K98/G98*100)
E99: 3.2.3. | F99: Majalah, Surat Kabar dan Buku | G99: 9.255 | H99: 26.857 | I99: 30.171429 | J99: 8.992 | K99: =L99-J99 | L99: 11.219 | M99: =IF(I99=0,0,$K99/I99*100) | N99: =IF(G99=0,0,$K99/G99*100)
E100: 3.2.4. | F100: Premi CIS, CIT dan Fidelity Guarantee | G100: 0 | H100: 0 | J100: 0 | K100: =L100-J100 | L100: 0 | M100: =IF(I100=0,0,$K100/I100*100) | N100: =IF(G100=0,0,$K100/G100*100)
E101: 3.2.5. | F101: HUT | G101: 444.58667 | H101: 1067.0001 | I101: 1067 | J101: 3.5 | K101: =L101-J101 | L101: 3.5 | M101: =IF(I101=0,0,$K101/I101*100) | N101: =IF(G101=0,0,$K101/G101*100)
E102: 3.2.6. | F102: Jamuan Makan | G102: 152.54266 | H102: 594.74126 | I102: 429 | J102: 205.38514 | K102: =L102-J102 | L102: 266.06377 | M102: =IF(I102=0,0,$K102/I102*100) | N102: =IF(G102=0,0,$K102/G102*100)
E103: 3.2.7. | F103: Olah Raga | G103: 376.39481 | H103: 765.02271 | I103: 787.28472 | J103: 344.02186 | K103: =L103-J103 | L103: 501.3734 | M103: =IF(I103=0,0,$K103/I103*100) | N103: =IF(G103=0,0,$K103/G103*100)
E104: 3.2.8. | F104: Humas & Publikasi | G104: 666.32114 | H104: 1431.15 | I104: 1576.5 | J104: 400.28934 | K104: =L104-J104 | L104: 514.85495 | M104: =IF(I104=0,0,$K104/I104*100) | N104: =IF(G104=0,0,$K104/G104*100)
E105: Sub Jumlah | G105: 1958.0347 | H105: 4895.1078 | I105: 4909.499 | J105: 1141.1664 | K105: =L105-J105 | L105: 1494.8141 | M105: =IF(I105=0,0,$K105/I105*100) | N105: =IF(G105=0,0,$K105/G105*100)
D107: JUMLAH BEBAN KANTOR | G107: 2413.5545 | H107: 6132.4626 | I107: 6570.8704 | J107: 1525.3711 | K107: =L107-J107 | L107: 1960.5478 | M107: =IF(I107=0,0,$K107/I107*100) | N107: =IF(G107=0,0,$K107/G107*100)
C110: 4. | D110: BEBAN KOMUNIKASI
D111: 4.1. | E111: Telepon dan Fax | G111: 20.56521 | H111: 54.712004 | I111: 60.342857 | J111: 17.242471 | K111: =L111-J111 | L111: 20.691175 | M111: =IF(I111=0,0,$K111/I111*100) | N111: =IF(G111=0,0,$K111/G111*100)
D112: 4.2. | E112: I n t e r n e t | G112: 1677.6946 | H112: 6407.4012 | I112: 7345.7178 | J112: 1264.83 | K112: =L112-J112 | L112: 1786.4014 | M112: =IF(I112=0,0,$K112/I112*100) | N112: =IF(G112=0,0,$K112/G112*100)
D113: 4.3. | E113: P o s | G113: 0 | H113: 0 | J113: 0 | K113: =L113-J113 | L113: 0 | M113: =IF(I113=0,0,$K113/I113*100) | N113: =IF(G113=0,0,$K113/G113*100)
D114: 4.4. | E114: E k s p e d i s i | G114: 42.95453 | H114: 105.59797 | I114: 98.287134 | J114: 41.636138 | K114: =L114-J114 | L114: 44.459011 | M114: =IF(I114=0,0,$K114/I114*100) | N114: =IF(G114=0,0,$K114/G114*100)
D115: JUMLAH BEBAN KOMUNIKASI | G115: 1741.2143 | H115: 6567.7112 | I115: 7504.3478 | J115: 1323.7086 | K115: =L115-J115 | L115: 1851.5516 | M115: =IF(I115=0,0,$K115/I115*100) | N115: =IF(G115=0,0,$K115/G115*100)
C117: 5. | D117: BEBAN TRANSPORTASI DAN KENDARAAN
...

Sheet Opex
C2: 2026
B3: Dalam Rp Juta | C3: RKAP | D3: YTD Mei
B4: Beban Pegawai | C4: 103922.39
B5: Beban Umum | C5: 16315.182
B6: Beban Administrasi | C6: 13374.459
B7: Beban IT | C7: 10912.718
B8: Beban Peny. & Amort. | C8: 17302.446
B9: Total Beban Usaha | C9: 161827.2
C11: 2026
B12: Dalam Rp Juta | C12: RKAP | D12: YTD Mei
B13: Gaji Manajemen | C13: 8645.752
B14: Gaji Pegawai | C14: 37922.72
B15: Honor Outsourcing | C15: 5244.4213
B16: Tantiem | C16: 4214.0406
B17: Jasa Produksi | C17: 6320.4534
B18: Tunjangan Hari Raya | C18: 6829.21
B19: Tunjangan Cuti | C19: 3665.8629
B20: Tunjangan Pendidikan | C20: 2796.8036
B21: Tunjangan Periodik | C21: 6157.0336
B22: Jamsostek | C22: 2299.2233
B23: Pengobatan/Medis | C23: 5122.594
B24: Tunjangan Hari Tua | C24: 4167.9761
... B27: Total Beban Pegawai | C27: 103922.39
C30: 2026
B31: Dalam Rp Juta | C31: RKAP | D31: YTD Mei
B32: Konsultan | C32: 7400
B33: Perjalanan Dinas | C33: 2482.4293
B34: Pendidikan & Pelatihan | C34: 3195.1681
B35: Iuran Keanggotaan | C35: 2193.0702
B36: Lain-lain | C36: 1044.5143
B37: Total Beban Umum | C37: 16315.182
C41: 2026
B42: Dalam Rp Juta | C42: RKAP | D42: YTD April
B43: Sewa Gedung | C43: 158.4
B44: Listrik & Air | C44: 428.05714
B45: Perawatan Kantor | C45: 493.14012
B46: Sewa Rumah Dinas | C46: 1878.8156
B47: BBM, Parkir, Tol | C47: 2718.0195
B48: Transportasi | C48: 818.52586
B49: Kegiatan Kantor (Cth: HUT) | C49: 1067
B50: Humas | C50: 1576.5
B51: Olah raga | C51: 787.28472
B52: Photo Copy & ATK | C52: 1286.3714
B53: Sumbangan/TJSL | C53: 946
B54: Keperluan Dapur | C54: 375
... B56: Total Beban Administrasi | C56: 13374.459
C60: 2026
B61: Dalam Rp Juta | C61: RKAP | D61: YTD April
B62: Internet | C62: 7345.7178
B63: Perlengkapan Komputer | C63: 2032
B64: Lain-lain | C64: 1535
B65: Total Beban IT | C65: 10912.718
C69: 2026
B70: Dalam Rp Juta | C70: RKAP | D70: YTD April
B71: Penyusutan Aset Tetap | C71: 4709.1799
B72: Penyusutan Amortisasi Tidak Berwujud | C72: 1716.2797
B73: Beban Hak Guna Usaha | C73: 10876.986
B74: Total Beban Peny. & Amort | C74: 17302.446

Sheet Belanja Modal
B2: Realisasi Belanja Modal PT JPAS Periode sd 31 Mei 2026
E4: Dalam Juta Rupiah
B5: NO | C5: KETERANGAN | D5: ANGGARAN RKAP 2026 | E5: REALISASI s.d 31 Mei 2026 | F5: %
B6: 1 | C6: TANAH GEDUNG KANTOR | D6: 0 | E6: 0 | F6: =IF(D6>0,(E6/D6),0)
B7: 2 | C7: GEDUNG KANTOR | D7: 0 | E7: 0 | F7: =IF(D7>0,(E7/D7),0)
B8: 3 | C8: RENOVASI GEDUNG KANTOR | D8: 500000000 | E8: 25705860 | F8: =IF(D8>0,(E8/D8),0)
B9: 4 | C9: INVENTARIS GEDUNG KANTOR | D9: 402400000 | E9: 17148000 | F9: =IF(D9>0,(E9/D9),0)
B10: 5 | C10: RENOVASI RUMAH JABATAN | D10: 0 | E10: 0 | F10: =IF(D10>0,(E10/D10),0)
B11: 6 | C11: INVENTARIS RUMAH JABATAN | D11: 0 | E11: 0 | F11: =IF(D11>0,(E11/D11),0)
B12: 7 | C12: KENDARAAN DINAS RODA DUA | D12: 0 | E12: 0 | F12: =IF(D12>0,(E12/D12),0)
B13: 8 | C13: KENDARAAN DINAS RODA EMPAT | D13: 2294148000 | E13: 0 | F13: =IF(D13>0,(E13/D13),0)
B14: 9 | C14: MESIN KANTOR | D14: 194600000 | E14: 39620918 | F14: =IF(D14>0,(E14/D14),0)
B15: 10 | C15: SOFTWARE KOMPUTER | D15: 4850000000 | E15: 0 | F15: =IF(D15>0,(E15/D15),0)
B16: 11 | C16: HARDWARE KOMPUTER | D16: 1300000000 | E16: 22300000 | F16: =IF(D16>0,(E16/D16),0)
B17: TOTAL BELANJA MODAL | D17: =SUM(D6:D16) | E17: 104774778 | F17: =IF(D17>0,(E17/D17),0)

Sheet Listing Accrual
B1: LISTING ACCRUAL BIAYA
B2: Periode Mei 2026
B4: No | C4: Keterangan | D4: Nominal
B5: 1 | C5: Accru Tantiem | D5: 13010596714
B6: 2 | C6: Accru Jasa Produksi | D6: 5.6319396e+09
B7: 3 | C7: Fee Subrograsi | D7: 1.1871027e+09
B8: 4 | C8: Accru THR | D8: 5.0574244e+09
B9: 5 | C9: Accru Biaya Audit | D9: 2.0301828e+09
B10: 6 | C10: Accru Div Sekper dan Legal | D10: 9.3379392e+08
B11: 7 | C11: Accru Div SDM dan Umum | D11: 9.5800867e+09
B12: 8 | C12: Accru Capex | D12: 239521792
B13: 9 | C13: Accru Pemasaran | D13: 197135600
B14: Total | D14: 3.7867784e+10

Sheet Subrogasi + SHS
A1: RECOVERY & SHS SD 31 Mei 2026
A2: #data dalam Juta Rupiah
B4: Makful Lahu | C4: Recoveries | D4: SHS
B5: BSI, Tbk. | C5: 1.9207064e+10 | D5: 8.8516214e+11
B6: PNM | C6: 4845118492 | D6: 6.2212397e+11
B7: BPD Riau | C7: 4.6138511e+08 | D7: 1.6092188e+10
B8: Pegadaian | C8: 221109063 | D8: 4.8219661e+09
B9: NTB Syariah | C9: 1.727535e+08 | D9: 1.1311039e+10
B10: LAINNYA | C10: =C11-SUM(C5:C9) | D10: =D11-SUM(D5:D9)
B11: Total | C11: 2.5534032e+10 | D11: 1.6766467e+12
C12: =SUM(C5:C9) | D12: =SUM(D5:D9)
B13: =SUM(C5:C9) | C13: 5.7503562e+09 | D13: =SUM(D5:D9)

Sheet Gearing Ratio
B3: Periode Mei 2026 | F3: dalam juta Rupiah
B4: Keterangan | D4: Usaha Produktif | E4: Usaha Non-Produktif | F4: Jumlah
B6: Nilai Penjaminan yang Ditanggung Sendiri | D6: 21845483492679 | E6: 13938471246113 | F6: 35783954738792
B7: Modal Sendiri Bersih | D7: 1.2068706e+12 | E7: 1.2068706e+12 | F7: 1.2068706e+12
B8: Gearing Ratio (Nilai Baris 1:2) | D8: 18.100933 | E8: 11.549268 | F8: 29.650201

Sheet Listing Aset Tetap
B2: Posisi 31 Mei 2026
B3: Aset Tetap | E3: Dalam Juta Rupiah
B4: Kategori | C4: Nilai Aset | D4: Akm Penyusutan | E4: Nilai Buku
B5: Tanah | C5: 4150998529 | E5: 4150998529
B6: Bangunan | C6: 814251471 | D6: -3.7659131e+08 | E6: 4.3766017e+08
B7: Kendaraan | C7: 871200000 | D7: -716925000 | E7: 154275000
B8: Peralatan Komputer | C8: 17928438362 | D8: -1.4322049e+10 | E8: 3.6063889e+09
B9: Peralatan Non Komputer | C9: 1.8395909e+09 | D9: -1.5427607e+09 | E9: 2.9683022e+08
B10: Perabot Kantor | C10: 4092231721 | D10: -3.0119633e+09 | E10: 1.0802684e+09
B11: Renovasi | C11: 1.6713767e+10 | D11: -8.8224709e+09 | E11: 7.8912962e+09
B12: Aset Hak Guna Usaha | C12: 1.9852748e+10 | D12: -1.1452997e+10 | E12: 8.399751e+09
B13: Aktiva Tetap dalam Penyelesaian | C13: 350324413 | E13: 350324413
B14: Total | C14: =SUM(C5:C13) | D14: =SUM(D5:D13) | E14: =SUM(E5:E13)
B16: Aset Tidak Berwujud
B17: Kategori | C17: Nilai Aset | D17: Akm Penyusutan | E17: Nilai Buku
B18: Software | C18: 9.6333161e+09 | D18: -7.9864569e+09 | E18: 1.6468591e+09
B19: Aktiva tak berwujud dalam penyelesaian | C19: 200000000 | E19: 200000000
B20: Beban Ditangguhkan Biaya Pendirian | C20: 977196699 | D20: -977196699 | E20: 0
B21: Total | C21: =SUM(C18:C20) | D21: =SUM(D18:D20) | E21: =SUM(E18:E20)

Sheet Piutang Ta'widh Re
A2: Periode 31 Mei 2026 | I2: Jutaan Rupiah
A3: Sum of PIUTANG | B3: Column Labels
A4: Keterangan | B4: 0-30 | C4: 31-60 | D4: 61-90 | E4: 91-120 | F4: 121-365 | G4: >365 | H4: CKPN | I4: Grand Total
A5: KONSUMTIF | B5: 3.3076824e+09 | C5: 1.3413764e+09 | D5: 9.2315452e+08 | E5: 1.7039348e+09 | F5: 7.1688882e+09 | G5: 4.0240454e+09 | H5: 0 | I5: =SUM(B5:H5)
A6: BANK JATENG SYARIAH | D6: 63248050 | F6: 47718945 | G6: 48526828 | H6: 0 | I6: =SUM(B6:H6)
A7: KOPERASI PEGAWAI PELABUHAN INDONESIA (KOPPELINDO) III | F7: 74742135 | H7: 0 | I7: =SUM(B7:H7)
A8: KOPPELINDO III SURABAYA | G8: 25000000 | H8: 0 | I8: =SUM(B8:H8)
A9: PT BANK ACEH SYARIAH | F9: 126293618 | G9: 26681746 | H9: 0 | I9: =SUM(B9:H9)
A10: PT BANK JABAR BANTEN SYARIAH | B10: 1.8101528e+08 | C10: 57586177 | D10: 13190654 | E10: 2.1940474e+08 | F10: 7.6688749e+08 | G10: 2.8555124e+08 | H10: 0 | I10: =SUM(B10:H10)
A11: PT BANK MUAMALAT INDONESIA TBK | G11: 81693720 | H11: 0 | I11: =SUM(B11:H11)
A12: PT BANK NTB SYARIAH | C12: 83097818 | F12: 6.0097602e+08 | G12: 2.0730868e+08 | H12: 0 | I12: =SUM(B12:H12)
A13: PT BANK SYARIAH NASIONAL | E13: 15060445 | F13: 4364995 | H13: 0 | I13: =SUM(B13:H13)
A14: PT BPD KALIMANTAN BARAT | B14: 2.0302378e+08 | D14: 58236196 | F14: 1.1684058e+08 | H14: 0 | I14: =SUM(B14:H14)
A15: PT BPD SULSEL DAN SULBAR | F15: 0 | H15: 0 | I15: =SUM(B15:H15)
A16: PT BPD SUMSELBABEL | G16: 26891794 | H16: 0 | I16: =SUM(B16:H16)
A17: PT BPRS BHAKTI SUMEKAR | E17: 42746770 | F17: 14407623 | H17: 0 | I17: =SUM(B17:H17)
A18: PT BPRS HIK | E18: 79328203 | F18: 13081328 | G18: 39724961 | H18: 0 | I18: =SUM(B18:H18)
A19: PT BPRS HIK BEKASI | G19: 0 | H19: 0 | I19: =SUM(B19:H19)
A20: PT BSI Tbk | B20: 2.9236433e+09 | C20: 1.1940183e+09 | D20: 7.8847962e+08 | E20: 1.2184748e+09 | F20: 5.3895961e+09 | G20: 3.2825326e+09 | H20: 0 | I20: =SUM(B20:H20)
A21: PT PNM | F21: 413600 | G21: 133800 | H21: 0 | I21: =SUM(B21:H21)
A22: PT BPR SYARIAH DINAR ASHRI | C22: 6674094.2 | E22: 1.2891991e+08 | F22: 13565732 | G22: 0 | H22: 0 | I22: =SUM(B22:H22)
A23: KUR | B23: 8.1094039e+09 | C23: 7.3945798e+09 | D23: 5.0854649e+09 | E23: 5.2951871e+09 | F23: 7.7760509e+09 | G23: 92853557 | H23: 0 | I23: =SUM(B23:H23)
A24: BANK JATENG SYARIAH | B24: 26919140 | C24: 2.4938634e+08 | D24: 50809770 | E24: 1.1292946e+08 | F24: 1.343888e+08 | G24: 0 | H24: 0 | I24: =SUM(B24:H24)
A25: BANK KALSEL SYARIAH | C25: 33003093 | H25: 0 | I25: =SUM(B25:H25)
A26: BANK NAGARI SYARIAH | C26: 22417800 | E26: 1675846.5 | F26: 278363.73 | G26: 11714653 | H26: 0 | I26: =SUM(B26:H26)
A27: PT BANK ACEH SYARIAH | B27: 54864410 | C27: 27372128 | D27: 63613390 | E27: 45064989 | F27: 1.4386696e+08 | H27: 0 | I27: =SUM(B27:H27)
A28: PT BANK RIAU KEPRI SYARIAH | B28: 1.001387e+08 | C28: 3.5483893e+08 | D28: 1.8416047e+08 | E28: 2.1351059e+08 | F28: 6.3434838e+08 | G28: 1.4901161e-08 | H28: 0 | I28: =SUM(B28:H28)
A29: PT BPD DIY | B29: 49175551 | D29: 61673848 | E29: 62002850 | F29: 9157413.4 | H29: 0 | I29: =SUM(B29:H29)
A30: PT BPD JATIM Tbk | B30: 10943764 | D30: 8740193.3 | E30: 21659292 | F30: 725797.24 | G30: -0.25 | H30: 0 | I30: =SUM(B30:H30)
A31: PT BSI Tbk | B31: 7.78316e+09 | C31: 6.572926e+09 | D31: 4.6122977e+09 | E31: 4.7541578e+09 | F31: 6.6205022e+09 | G31: 81138904 | H31: 0 | I31: =SUM(B31:H31)
A32: PT PEGADAIAN | B32: 84202339 | C32: 1.346355e+08 | D32: 1.041696e+08 | E32: 84186250 | F32: 2.3278297e+08 | G32: 0 | H32: 0 | I32: =SUM(B32:H32)
A33: MIKRO | B33: 5.3807565e+09 | C33: 5.098013e+09 | D33: 6.348377e+09 | E33: 9.1454266e+09 | F33: 2.7891307e+09 | G33: 2.4640675e+09 | H33: 0 | I33: =SUM(B33:H33)
A34: BANK NAGARI SYARIAH | F34: 7907634.7 | G34: 1642109.6 | H34: 0 | I34: =SUM(B34:H34)
A35: PT BSI Tbk | B35: 7.9887174e+08 | C35: 615276823 | D35: 5.9537263e+08 | E35: 1.4922901e+09 | F35: 2.9669596e+08 | G35: 3.8930912e+08 | H35: 0 | I35: =SUM(B35:H35)
A36: PT PNM | B36: 4.5818848e+09 | C36: 4.4827362e+09 | D36: 5.7530044e+09 | E36: 7.6531365e+09 | F36: 2.4845271e+09 | G36: 2.0731163e+09 | H36: 0 | I36: =SUM(B36:H36)
A37: PEN | G37: 1.2469668e+08 | H37: 0 | I37: =SUM(B37:H37)
A38: BTPN SYARIAH | G38: 1.2469668e+08 | H38: 0 | I38: =SUM(B38:H38)
A39: Retail & Korporasi | B39: 30364885 | D39: 9040109.6 | F39: 0 | G39: 0 | H39: 0 | I39: =SUM(B39:H39)
A40: PT BANK NTB SYARIAH | B40: 30364885 | F40: 0 | H40: 0 | I40: =SUM(B40:H40)
A41: PT BPD JATIM Tbk | D41: 9040109.6 | H41: 0 | I41: =SUM(B41:H41)
A42: PT BSI Tbk | G42: 0 | H42: 0 | I42: =SUM(B42:H42)
A43: PT BPD JATIM Tbk | B43: 9040109.6 | C43: 0 | D43: 0 | E43: 0 | F43: 0 | G43: 0 | H43: 0 | I43: =SUM(B43:H43)
A44: PT BSI Tbk | B44: 0 | C44: 0 | D44: 0 | E44: 0 | F44: 0 | G44: 0 | H44: 0 | I44: =SUM(B44:H44)
A45: CKPN | B45: 0 | C45: 0 | D45: 0 | E45: 0 | F45: 0 | G45: 0 | H45: -8.9986309e+08 | I45: -8.9986309e+08
A46: Grand Total | B46: =B5+B23+B33+B37+B39 | C46: =C5+C23+C33+C37+C39 | D46: =D5+D23+D33+D37+D39 | E46: =E5+E23+E33+E37+E39 | F46: =F5+F23+F33+F37+F39 | G46: =G5+G23+G33+G37+G39 | H46: =H5+H25+H35+H39+H41+H45 | I46: =SUM(B46:H46)

Sheet Piutang IJK
B1: Posisi Mei 2026 | K1: Dalam Juta Rupiah
B2: Sum of Piutang IJK per 31 Oktober 2025 | C2: Column Labels
B3: Row Labels | C3: 0-30 | D3: 31-60 | E3: 61-90 | F3: 91-120 | G3: 121-180 | H3: 181-365 | I3: >365 | J3: CKPN | K3: Grand Total
B4: RETAIL & KORPORASI | C4: 180000 | I4: 4.8654029e+08 | J4: 0 | K4: =SUM(C4:I4)
B5: BANK JATENG SYARIAH | I5: 9865000 | J5: 0 | K5: =SUM(C5:I5)
B6: BANK JATIM SYARIAH | I6: 12169500 | J6: 0 | K6: =SUM(C6:I6)
B7: PT BANK ACEH SYARIAH | C7: 60000 | I7: 2883200 | J7: 0 | K7: =SUM(C7:I7)
B8: PT BANK JABAR BANTEN SYARIAH | I8: 596000 | J8: 0 | K8: =SUM(C8:I8)
B9: PT BANK MUAMALAT INDONESIA Tbk | I9: 19551180 | J9: 0 | K9: =SUM(C9:I9)
B10: PT BANK NTB SYARIAH | I10: 3425500 | J10: 0 | K10: =SUM(C10:I10)
B11: PT BSI Tbk | C11: 120000 | I11: 4.2463391e+08 | J11: 0 | K11: =SUM(C11:I11)
B12: PT CIMB NIAGA SYARIAH | I12: 5800000 | J12: 0 | K12: =SUM(C12:I12)
B13: PT SAHABAT FINANSIAL KELUARGA | I13: 7616000 | J13: 0 | K13: =SUM(C13:I13)
B14: MIKRO | C14: 4900000 | D14: 960626 | E14: 1630000 | F14: 60000 | I14: 4.4602934e+08 | J14: 0 | K14: =SUM(C14:I14)
B15: BANK NAGARI SYARIAH | I15: 1885000 | J15: 0 | K15: =SUM(C15:I15)
B16: PT BSI Tbk | C16: 4890000 | D16: 960626 | E16: 1630000 | F16: 60000 | I16: 4.4400423e+08 | J16: 0 | K16: =SUM(C16:I16)
B17: PT PNM | C17: 10000 | I17: 140113.6 | J17: 0 | K17: =SUM(C17:I17)
B18: KONSUMTIF | C18: -27228854 | D18: 100000 | F18: 529721 | H18: -30000 | I18: 4.2624713e+08 | J18: 0 | K18: =SUM(C18:I18)
B19: BANK JATIM SYARIAH | C19: 60000 | J19: 0 | K19: =SUM(C19:I19)
B20: BANK SUMSELBABEL SYARIAH | I20: 4163384 | J20: 0 | K20: =SUM(C20:I20)
B21: BPRS DINAR ASHRI | I21: -4317069 | J21: 0 | K21: =SUM(C21:I21)
B22: PT BANK JABAR BANTEN SYARIAH | C22: -4916851 | D22: 100000 | F22: 529721 | I22: 8006354 | J22: 0 | K22: =SUM(C22:I22)
B23: PT BANK NTB SYARIAH | I23: 12665000 | J23: 0 | K23: =SUM(C23:I23)
B24: PT BSI Tbk | C24: -22372003 | H24: -30000 | I24: 4.0572946e+08 | J24: 0 | K24: =SUM(C24:I24)
B25: KUR | C25: 79586889 | D25: 53892358 | E25: 13461846 | F25: 3160810 | G25: 24680982 | H25: 63680913 | I25: 54208065 | J25: 0 | K25: =SUM(C25:I25)
B26: BANK JATENG SYARIAH | C26: 15331569 | D26: 6905097 | E26: 7600027 | F26: 2259711 | J26: 0 | K26: =SUM(C26:I26)
B27: BANK JATIM SYARIAH | C27: 22219919 | D27: 12315172 | E27: 448000 | J27: 0 | K27: =SUM(C27:I27)
B28: BANK KALBAR SYARIAH | C28: 23396365 | J28: 0 | K28: =SUM(C28:I28)
B29: BANK NAGARI SYARIAH | D29: 353787 | E29: 353787 | G29: 1078208 | H29: 66642925 | I29: 65899113 | J29: 0 | K29: =SUM(C29:I29)
B30: PT BANK ACEH SYARIAH | C30: 3294201 | D30: 10918302 | J30: 0 | K30: =SUM(C30:I30)
B31: PT BSI Tbk | C31: 15344835 | D31: 23400000 | E31: 5060032 | F31: 901099 | G31: 23602774 | H31: -2962012 | I31: -11691048 | J31: 0 | K31: =SUM(C31:I31)
B32: KBG | D32: 41725000 | I32: 1.3594601e+08 | J32: 0 | K32: =SUM(C32:I32)
B33: EXIMBANK INDONESIA | I33: 5155000 | J33: 0 | K33: =SUM(C33:I33)
B34: PT BANK ACEH SYARIAH | I34: 2487917 | J34: 0 | K34: =SUM(C34:I34)
B35: PT BANK NTB SYARIAH | I35: 1482620.1 | J35: 0 | K35: =SUM(C35:I35)
B36: PT BSI Tbk | D36: 41725000 | I36: 1.0661669e+08 | J36: 0 | K36: =SUM(C36:I36)
B37: PT BTPN SYARIAH Tbk | I37: 511250 | J37: 0 | K37: =SUM(C37:I37)
B38: PT GRAND MECCA HOLIDAYS | I38: 106000 | J38: 0 | K38: =SUM(C38:I38)
B39: PT KB BUKOPIN SYARIAH | I39: 19586534 | J39: 0 | K39: =SUM(C39:I39)
B40: KPP | C40: 25964000 | E40: 11700000 | F40: 31650000 | J40: 0 | K40: =SUM(C40:I40)
B41: BANK JATENG SYARIAH | C41: 10764000 | E41: 11700000 | F41: 31650000 | J41: 0 | K41: =SUM(C41:I41)
B42: PT BSI Tbk | C42: 15200000 | J42: 0 | K42: =SUM(C42:I42)
B43: PEN | I43: 62408603 | J43: 0 | K43: =SUM(C43:I43)
B44: BANK MAYBANK SYARIAH INDONESIA | I44: 127194 | J44: 0 | K44: =SUM(C44:I44)
B45: PT BANK ACEH SYARIAH | I45: 219291 | J45: 0 | K45: =SUM(C45:I45)
B46: PT BPD DI YOGYAKARTA | I46: 167397 | J46: 0 | K46: =SUM(C46:I46)
B47: PT BSI Tbk | I47: 50518106 | J47: 0 | K47: =SUM(C47:I47)
B48: PT BTPN SYARIAH Tbk | I48: 11376615 | J48: 0 | K48: =SUM(C48:I48)
B49: SURETY | I49: 25870867 | J49: 0 | K49: =SUM(C49:I49)
B50: PSTNT - BATAN | I50: 134850 | J50: 0 | K50: =SUM(C50:I50)
B51: PT BANK ACEH SYARIAH | I51: 1224000 | J51: 0 | K51: =SUM(C51:I51)
B52: PT BANK JABAR BANTEN SYARIAH | I52: 682600 | J52: 0 | K52: =SUM(C52:I52)
B53: PT BTPN SYARIAH Tbk | I53: 1101670 | J53: 0 | K53: =SUM(C53:I53)
B54: SURETY | I54: 22727747 | J54: 0 | K54: =SUM(C54:I54)
B55: CKPN | C55: 0 | D55: 0 | E55: 0 | F55: 0 | G55: 0 | H55: 0 | I55: 0 | J55: -1627000000 | K55: -1627000000
B56: Grand Total | C56: =C4+C14+C18+C25+C32+C40+C43+C49+C55 | D56: =D4+D14+D18+D25+D32+D40+D43+D49+D55 | E56: =E4+E14+E18+E25+E32+E40+E43+E49+E55 | F56: =F4+F14+F18+F25+F32+F40+F43+F49+F55 | G56: =G4+G14+G18+G25+G32+G40+G43+G49+G55 | H56: =H4+H14+H18+H25+H32+H40+H43+H49+H55 | I56: =I4+I14+I18+I25+I32+I40+I43+I49+I55 | J56: =J4+J14+J18+J25+J32+J40+J43+J49+J55 | K56: =K4+K14+K18+K25+K32+K40+K43+K49+K55

Sheet Cadangan Teknis
H2: Dalam Juta Rupiah
A3: No | B3: Class Of Business | C3: Balance | F3: Kenaikan (Penurunan)
C4: Mei 2026 | F4: Mei 26 - Des 25
C5: GROSS | D5: NET | E5: Aset Reas | F5: GROSS | G5: NET | H5: Aset Reas
A7: Cadangan Premi
A8: 1 | B8: KUR | C8: 8.8544929e+11 | D8: 6.3711083e+11 | E8: 2.4833846e+11 | F8: -4.1903352e+09 | G8: 5.3994189e+09 | H8: -9.5897541e+09
A9: 2 | B9: MIKRO | C9: 2.8989327e+11 | D9: 1.9901456e+11 | E9: 9.0878704e+10 | F9: 3.4835423e+10 | G9: 2.9282313e+10 | H9: 5.5531101e+09
A10: 3 | B10: PEN | C10: 0 | D10: 0 | E10: 0 | F10: 0 | G10: 0 | H10: 0
A11: 4 | B11: PRODUKTIF LAINNYA | C11: 3.9636333e+10 | D11: 1.9488663e+10 | E11: 2.014767e+10 | F11: -5.0986341e+09 | G11: -1.5603493e+09 | H11: -3.5382848e+09
A12: 5 | B12: KONSUMTIF | C12: 2.0086082e+11 | D12: 1.0284458e+11 | E12: 9.8016238e+10 | F12: -5.1714779e+09 | G12: 7.6386954e+08 | H12: -5.9353474e+09
A13: 6 | B13: KBG & SURETY | C13: 4.8971137e+09 | D13: 3.249433e+09 | E13: 1.6476807e+09 | F13: 1.1258891e+09 | G13: 4.9480977e+08 | H13: 6.3107931e+08
A14: 7 | B14: KPP | C14: 4.5082701e+10 | E14: 1.1270675e+10 | F14: 4.2300238e+10 | G14: -2.0868469e+09 | H14: 1.057506e+10
A15: TOTAL CADANGAN PREMI | C15: 1.4658195e+12 | D15: 9.6170807e+11 | E15: 4.7029943e+11 | F15: 6.3801103e+10 | G15: 3.2293215e+10 | H15: -2.3041374e+09
A16: R/I Comm
A17: 1 | B17: KUR | C17: 7.1511154e+10 | F17: -4.5989555e+09 | G17: 0 | H17: 0
A18: 2 | B18: MIKRO | C18: 2.6122299e+10 | F18: 5.3642607e+08 | G18: 0 | H18: 0
A19: 3 | B19: PEN | C19: 0 | F19: 0 | G19: 0 | H19: 0
A20: 4 | B20: PRODUKTIF LAINNYA | C20: 5.1764211e+09 | F20: -8.5097398e+08 | G20: 0 | H20: 0
A21: 5 | B21: KONSUMTIF | C21: 2.134195e+10 | F21: -1.2940655e+09 | G21: 0 | H21: 0
A22: 6 | B22: KBG & SURETY | C22: 4.5450518e+08 | F22: 1.3938597e+08 | G22: 0 | H22: 0
A23: 7 | B23: KPP | C23: 2.850058e+09 | F23: 2.6413733e+09 | G23: 0 | H23: 0
A24: TOTAL R/I COM | C24: 1.2745639e+11 | D24: 0 | E24: 0 | F24: -3.4268096e+09 | G24: 0 | H24: 0
A27: IBNR (Incurred But Not Reported)
A28: 1 | B28: KUR | C28: 3.4712977e+10 | D28: 2.2757582e+10 | E28: 11955394736 | F28: 1.9826405e+09 | G28: 3.9067442e+09 | H28: -1.9241037e+09
A29: 2 | B29: MIKRO | C29: 8.5428212e+10 | D29: 6.8361141e+10 | E29: 17067070507 | F29: 4.6119065e+09 | G29: 7.306586e+08 | H29: 3.8812479e+09
A30: 3 | B30: PEN | C30: 0 | D30: 0 | E30: 0 | F30: 0 | G30: 0 | H30: 0
A31: 4 | B31: PRODUKTIF LAINNYA | C31: -1.5487864e+10 | D31: -1.909151e+10 | E31: 3603646389 | F31: -2.6260831e+09 | G31: -5.8152002e+08 | H31: -2.0445631e+09
A32: 5 | B32: KONSUMTIF | C32: 1.0082143e+10 | D32: 1.5453574e+09 | E32: 8536785219 | F32: -2.5950121e+09 | G32: -5.3065998e+09 | H32: 2.7115877e+09
A33: 6 | B33: KBG & SURETY | C33: 5.4853894e+08 | D33: 1.5847579e+08 | E33: 390063146 | F33: -6.3462672e+08 | G33: -1.1279677e+08 | H33: -5.2182995e+08
A34: 7 | B34: KPP | C34: 0 | D34: 0 | E34: 0 | F34: 0 | G34: 0 | H34: 0
A35: TOTAL IBNR | C35: 1.1528401e+11 | D35: 7.3731047e+10 | E35: 41552959997 | F35: 7.3882505e+08 | G35: -1.3635138e+09 | H35: 2.1023388e+09
A36: OS Claim
A37: 1 | B37: KUR | C37: 2.2980767e+11 | D37: 1.602556e+11 | E37: 6.9552075e+10 | F37: 2.5308071e+10 | G37: 1.7033713e+10 | H37: 8.2743573e+09
A38: 2 | B38: MIKRO | C38: 4.8845066e+09 | D38: 2.1013695e+09 | E38: 2.7831371e+09 | F38: -1.9170795e+08 | G38: -2.8248868e+08 | H38: 90780727
A39: 3 | B39: PEN | C39: 0 | D39: 0 | E39: 0 | F39: 0 | G39: 0 | H39: 0
A40: 4 | B40: PRODUKTIF LAINNYA | C40: 9.4980498e+10 | D40: 3.805382e+10 | E40: 5.6926678e+10 | F40: -3.3616376e+08 | G40: 1.2154964e+08 | H40: -4.577134e+08
A41: 5 | B41: KONSUMTIF | C41: 1.3648172e+10 | D41: 5.5480758e+09 | E41: 8.1000965e+09 | F41: 1.6388305e+09 | G41: 1.2320206e+09 | H41: 4.0680992e+08
A42: 6 | B42: KBG & SURETY | C42: 760110400 | D42: 532077280 | E42: 228033120 | F42: 0 | G42: 0 | H42: 0
A43: 7 | B43: KPP | C43: 0 | D43: 0 | E43: 0 | F43: 0 | G43: 0 | H43: 0
A44: TOTAL OS CLAIM | C44: 3.4408096e+11 | D44: 2.0649094e+11 | E44: 1.3759002e+11 | F44: 2.6419029e+10 | G44: 1.8104795e+10 | H44: 8.3142345e+09
A45: Beban Akuisisi Tangguhan
A46: 1 | B46: KUR | C46: 0 | F46: 0 | G46: 0 | H46: 0
A47: 2 | B47: MIKRO | C47: 1.956989e+10 | F47: 2.7315404e+09 | G47: 0 | H47: 0
A48: 3 | B48: PEN | C48: 0 | F48: 0 | G48: 0 | H48: 0
A49: 4 | B49: PRODUKTIF LAINNYA | C49: 4.3709929e+08 | F49: -72275894 | G49: 0 | H49: 0
A50: 5 | B50: KONSUMTIF | C50: 1.7447997e+10 | F50: -1.2726199e+09 | G50: 0 | H50: 0
A51: 6 | B51: KBG & SURETY | C51: 40469908 | F51: -20074216 | G51: 0 | H51: 0
A52: 7 | B52: KPP | C52: 0 | F52: 0 | G52: 0 | H52: 0
A53: TOTAL BEBAN AKUISISI TANGGUHAN | C53: 3.7495456e+10 | D53: 0 | E53: 0 | F53: 1.3665704e+09 | G53: 0 | H53: 0
A54: Cadangan Klaim
A55: 1 | B55: KUR | C55: 2.6452065e+11 | D55: 1.8301318e+11 | E55: 8.150747e+10 | F55: 2.7290711e+10 | G55: 2.0940458e+10 | H55: 6.3502536e+09
A56: 2 | B56: MIKRO | C56: 9.0312718e+10 | D56: 7.0462511e+10 | E56: 1.9850208e+10 | F56: 4.4201985e+09 | G56: 4.4816992e+08 | H56: 3.9720286e+09
A57: 3 | B57: PEN | C57: 0 | D57: 0 | E57: 0 | F57: 0 | G57: 0 | H57: 0
A58: 4 | B58: PRODUKTIF LAINNYA | C58: 7.9492634e+10 | D58: 1.896231e+10 | E58: 6.0530324e+10 | F58: -2.9622469e+09 | G58: -4.5997038e+08 | H58: -2.5022765e+09
A59: 5 | B59: KONSUMTIF | C59: 2.3730315e+10 | D59: 7.0934332e+09 | E59: 1.6636882e+10 | F59: -9.5618155e+08 | G59: -4.0745792e+09 | H59: 3.1183976e+09
A60: 6 | B60: KBG & SURETY | C60: 1.3086493e+09 | D60: 6.9055307e+08 | E60: 618096266 | F60: -6.3462672e+08 | G60: -1.1279677e+08 | H60: -5.2182995e+08
A61: 7 | B61: KPP | C61: 0 | D61: 0 | E61: 0 | F61: 0 | G61: 0 | H61: 0
A62: TOTAL CADANGAN KLAIM | C62: 4.5936496e+11 | D62: 2.8022199e+11 | E62: 1.7914298e+11 | F62: 2.7157855e+10 | G62: 1.6741281e+10 | H62: 1.0416573e+10
A65: Cadangan Teknis (Cadangan Premi + Cadangan Klaim)
A66: 1 | B66: KUR | C66: 1.1499699e+12 | D66: 8.2012401e+11 | E66: 3.2984593e+11 | F66: 2.3100376e+10 | G66: 2.6339877e+10 | H66: -3.2395005e+09
A67: 2 | B67: MIKRO | C67: 3.8020598e+11 | D67: 2.6947707e+11 | E67: 1.1072891e+11 | F67: 3.9255622e+10 | G67: 2.9730483e+10 | H67: 9.5251387e+09
A68: 3 | B68: PEN | C68: 0 | D68: 0 | E68: 0 | F68: 0 | G68: 0 | H68: 0
A69: 4 | B69: PRODUKTIF LAINNYA | C69: 1.1912897e+11 | D69: 3.8450972e+10 | E69: 8.0677995e+10 | F69: -8.060881e+09 | G69: -2.0203197e+09 | H69: -6.0405613e+09
A70: 5 | B70: KONSUMTIF | C70: 2.2459113e+11 | D70: 1.0993801e+11 | E70: 1.1465312e+11 | F70: -6.1276594e+09 | G70: -3.3107096e+09 | H70: -2.8169498e+09
A71: 6 | B71: KBG & SURETY | C71: 6.205763e+09 | D71: 3.9399861e+09 | E71: 2.2657769e+09 | F71: 4.9126236e+08 | G71: 3.82013e+08 | H71: 1.0924936e+08
A72: 7 | B72: KPP | C72: 4.5082701e+10 | D72: 0 | E72: 1.1270675e+10 | F72: 4.2300238e+10 | G72: -2.0868469e+09 | H72: 1.057506e+10
A73: TOTAL CADANGAN TEKNIS | C73: 1.9251845e+12 | D73: 1.2419301e+12 | E73: 6.4944241e+11 | F73: 4.865872e+10 | G73: 5.1121343e+10 | H73: -2.4626236e+09

Sheet Per Bank Per COB Mei 2026
B1: YTD Mei 26 | F1: Dalam Juta Rupiah
C2: NAMA BANK | D2: IJK BRUTO | E2: BEBAN AKUISISI | F2: TAWIDH BRUTO | G2: NET BALANCE
C3: MIKRO | D3: 1.6576775e+11 | E3: 1.2566109e+10 | F3: 1.2690423e+11 | G3: 2.6297415e+10
C4: PT PNM | D4: 1.6058078e+11 | E4: 1.2566109e+10 | F4: 120514307582 | G4: 2.7500359e+10
C5: PT BSI Tbk | D5: 5.1869756e+09 | E5: 0 | F5: 6.3572407e+09 | G5: -1.1702651e+09
C6: PT BANK NAGARI | D6: 0 | E6: 0 | F6: 32679189 | G6: -32679189
C7: KUR | D7: 1.6506855e+11 | E7: 0 | F7: 9.9453924e+10 | G7: 6.5614623e+10
C8: PT BSI Tbk | D8: 1.5261564e+11 | E8: 0 | F8: 9.086333e+10 | G8: 6.1752306e+10
C9: PT PEGADAIAN | D9: 5223780702 | E9: 0 | F9: 1870242096 | G9: 3353538606
C10: PT BANK ACEH SYARIAH | D10: 2877576376 | E10: 0 | F10: 973499984 | G10: 1904076392
C11: BANK JATENG SYARIAH | D11: 1.5956568e+09 | E11: 0 | F11: 1623870216 | G11: -28213434
C12: PT BANK RIAU KEPRI SYARIAH | D12: 1338152500 | E12: 0 | F12: 3187733169 | G12: -1849580669
C13: PT BPD JATIM Tbk | D13: 6.8533643e+08 | E13: 0 | F13: 170829687 | G13: 5.1450675e+08
C14: PT BPD KALIMANTAN BARAT | D14: 231578196 | E14: 0 | F14: 0 | G14: 231578196
... C53: Grand Total | D53: 4.0507527e+11 | E53: 1.2568298e+10 | F53: 2.3854839e+11 | G53: 1.5395858e+11

Sheet Plafon Penjaminan per Mitra
C2: SEPULUH BESAR OS KAFALAH PER MITRA PT JPAS
C4: Mei 2026
F5: Dalam Juta Rupiah
C6: No | D6: Bank Induk | E6: Sum of OS_KAFALAH | F6: Sum of OS_PENJAMINAN
C7: 1 | D7: PT BSI Tbk | E7: 29229793636684 | F7: 13854629607077
C8: 2 | D8: PT PNM | E8: 13817787025062 | F8: 7768400742761
C9: 3 | D9: PT BANK SYARIAH NASIONAL | E9: 11763032026272 | F9: 10570186194002
C10: 4 | D10: PT BPRS DINAR ASHRI | E10: 1149800343303 | F10: 640561833313
C11: 5 | D11: PT BANK ACEH SYARIAH | E11: 768457216809 | F11: 349700421142
C12: 6 | D12: PT BANK JABAR BANTEN SYARIAH | E12: 684378513845 | F12: 197667554873
C13: 7 | D13: PT BANK RIAU KEPRI SYARIAH | E13: 658037175682 | F13: 307209322865
C14: 8 | D14: BANK JATENG SYARIAH | E14: 612314339413 | F14: 310438543312
C15: 9 | D15: PT PEGADAIAN | E15: 539295854465 | F15: 280762817594
C16: 10 | D16: LAINNYA | E16: 3149250183250 | F16: 1504397735290
C17: GRAND TOTAL | E17: =SUM(E7:E16) | F17: =SUM(F7:F16)

Sheet KUR
B2: KAFALAH KUR PT JPAS
B5: Mei 2026 | E5: Rupiah Penuh
B6: Row Labels | C6: Sum of Kafalah | D6: Count of Nama Debitur | E6: Sum of Ujrah
B7: KUR KECIL | C7: 3.4294525e+13 | D7: 147388 | E7: 1.3566255e+12
B8: PT BSI Tbk | C8: 3.11467e+13 | D8: 130034 | E8: 1.2349905e+12
B9: PT BANK RIAU KEPRI SYARIAH | C9: 1545768000000 | D9: 7384 | E9: 60322997638
B10: BANK JATENG SYARIAH | C10: 793595978856 | D10: 5383 | E10: 2.9427249e+10
B11: PT BANK ACEH SYARIAH | C11: 372706000000 | D11: 1359 | E11: 15044274428
B12: PT BPD DIY | C12: 219523000000 | D12: 929 | E12: 9346694189
B13: PT BPD JATIM Tbk | C13: 94117000000 | D13: 631 | E13: 2.3346936e+09
B14: PT BANK NAGARI | C14: 37990000000 | D14: 974 | E14: 2.3176045e+09
B15: BANK KALSEL SYARIAH | C15: 27571200000 | D15: 112 | E15: 1080820515
B16: PT BANK JABAR BANTEN SYARIAH | C16: 14603000000 | D16: 52 | E16: 605726510
B17: PT BPD KALIMANTAN BARAT | C17: 12185000000 | D17: 42 | E17: 532053535
B18: PT BPD KALTIM KALTARA | C18: 6270000000 | D18: 23 | E18: 251744010
... B54: Grand Total | C54: 6.364922e+13 | D54: 701768 | E54: 2.4020258e+12

Sheet Utang Ta'widh
B1: Posisi Mei 2026 | H1: Dalam Juta Rupiah
B2: Keterangan | C2: 0 - 30 | D2: 31-60 | E2: 61-90 | F2: 91-120 | G2: 121-365 | H2: >365 | I2: Total
B3: MIKRO | C3: =SUM(C4:C4) | D3: 0 | E3: 0 | F3: 0 | G3: 0 | H3: 0 | I3: =SUM(C3:H3)
B4: PT BSI Tbk | C4: 35769640 | D4: 0 | E4: 0 | F4: 0 | G4: 0 | H4: 0 | I4: =SUM(C4:H4)
B5: KUR | C5: =SUM(C6:C6) | D5: 0 | E5: 0 | F5: 0 | G5: 0 | H5: 0 | I5: =SUM(C5:H5)
B6: PT PEGADAIAN | C6: 9512952 | D6: 0 | E6: 0 | F6: 0 | G6: 0 | H6: 0 | I6: =SUM(C6:H6)
B7: Grand Total | C7: =C3+C5 | D7: =D3+D5 | E7: =E3+E5 | F7: =F3+F5 | G7: =G3+G5 | H7: =H3+H5 | I7: =I3+I5

Sheet CFI_Model_Checks
A1: JPAS — CFI 3-Statement Integrity Checks
A2: All figures in IDR Jutaan (Millions) | Period: YTD Mei 2026
A4: CHECK 1 — BALANCE SHEET: Assets = Liabilities + Equity
B5: Item | C5: Formula Reference | D5: Mei 2026 (IDR Juta) | E5: Mei 2025 (IDR Juta) | F5: Δ YoY | G5: Status
B6: Total Assets (A) | D6: ='Summary BS KONSOL Mei 2026'!F6 | E6: ='Summary BS KONSOL Mei 2026'!I6 | F6: =D6-E6
B7: Total Liabilities (L) | D7: ='Summary BS KONSOL Mei 2026'!F26 | E7: ='Summary BS KONSOL Mei 2026'!I26 | F7: =D7-E7
B8: Total Equity (E) | D8: ='Summary BS KONSOL Mei 2026'!F43 | E8: ='Summary BS KONSOL Mei 2026'!I43 | F8: =D8-E8
B9: L + E | D9: =D7+D8
B10: BS Check (A − L − E) | D10: =D6-D7-D8 | G10: =IF(ABS(D10)<1,"✅ BALANCED","❌ OUT OF BALANCE")
A12: CHECK 2 — CASH TIE: CFS Ending Cash = BS Cash Balance
B13: Item | C13: Source Sheet | D13: Amount (IDR Juta) | G13: Status
B14: CFS — Kas dan Setara Kas Akhir Tahun | C14: CASH FLOW Mei 2026 | D14: ='CASH FLOW Mei 2026'!E36 | G14: =IF(ABS(D14-D15)<1,"✅ MATCH","❌ MISMATCH")
B15: BS — Kas dan Bank | C15: Summary BS | D15: ='Summary BS KONSOL Mei 2026'!F8
B16: Difference | D16: =D14-D15
A18: CHECK 3 — NET INCOME TIE: IS Net Income = BS Laba Tahun Berjalan
B19: Item | C19: Source Sheet | D19: Amount (IDR Juta) | G19: Status
B20: IS — Laba Setelah Pajak (Net Income) | C20: Summary PL | D20: ='Summary PL KONSOL Mei 2026'!F44 | G20: =IF(ABS(D20-D21)<1,"✅ MATCH","❌ MISMATCH")
B21: BS — Laba (Rugi) Tahun Berjalan | C21: Summary BS | D21: ='Summary BS KONSOL Mei 2026'!F47
B22: Difference | D22: =D20-D21
A24: COLOR LEGEND & NOTES
B25: 🔵 Blue Font = Hard-coded input value
B26: ⚫ Black Font = Same-sheet formula
B27: 🟢 Green Font = Cross-sheet link (source tab indicated in column C)
B28: Note: All checks use absolute cell references to source tabs — live-linked, not hardcoded.

Sheet CFI_Ratio_Analysis
A1: JPAS — Financial Ratio Analysis (CFI FMVA Module 1 Standards)
A2: All figures in IDR Jutaan | Period: YTD Mei 2026 | Ratios annualized where noted
B4: Ratio / Metric | C4: Formula | D4: Numerator (IDR Juta) | E4: Denominator (IDR Juta) | F4: YTD Mei 2026 | G4: YTD Mei 2025 | H4: Δ YoY (pp) | I4: Benchmark / Note
A6: SECTION 1 — PROFITABILITY RATIOS
B7: Gross UW Revenue (IJK Bruto) | C7: =Top-line IJK income | F7: ='Summary PL KONSOL Mei 2026'!F8 | G7: ='Summary PL KONSOL Mei 2026'!H8 | H7: =F7-G7 | I7: Top-line revenue
B8: Net UW Margin | C8: =Hasil UW Neto / IJK Bruto | D8: ='Summary PL KONSOL Mei 2026'!F24 | E8: ='Summary PL KONSOL Mei 2026'!F8 | F8: =D8/E8 | G8: ='Summary PL KONSOL Mei 2026'!H24/'Summary PL KONSOL Mei 2026'!H8 | H8: =F8-G8 | I8: Islamic takaful benchmark: >15%
B9: Net Profit Margin | C9: =Laba Setelah Pajak / IJK Bruto | D9: ='Summary PL KONSOL Mei 2026'!F44 | E9: ='Summary PL KONSOL Mei 2026'!F8 | F9: =D9/E9 | G9: ='Summary PL KONSOL Mei 2026'!H44/'Summary PL KONSOL Mei 2026'!H8 | H9: =F9-G9 | I9: General insurance: 10–20%
B10: EBIT Margin (Laba Usaha Margin) | C10: =Laba Usaha / IJK Bruto | D10: ='Summary PL KONSOL Mei 2026'!F34 | E10: ='Summary PL KONSOL Mei 2026'!F8 | F10: =D10/E10 | G10: ='Summary PL KONSOL Mei 2026'!H34/'Summary PL KONSOL Mei 2026'!H8 | H10: =F10-G10 | I10: Measures operating efficiency
B11: EBT Margin | C11: =Laba Sebelum Pajak / IJK Bruto | D11: ='Summary PL KONSOL Mei 2026'!F40 | E11: ='Summary PL KONSOL Mei 2026'!F8 | F11: =D11/E11 | G11: ='Summary PL KONSOL Mei 2026'!H40/'Summary PL KONSOL Mei 2026'!H8 | H11: =F11-G11 | I11: Pre-tax profitability
B12: Tax Rate (Effective) | C12: =Pajak / EBT | D12: ='Summary PL KONSOL Mei 2026'!F42 | E12: ='Summary PL KONSOL Mei 2026'!F40 | F12: =D12/E12 | G12: ='Summary PL KONSOL Mei 2026'!H42/'Summary PL KONSOL Mei 2026'!H40 | H12: =F12-G12 | I12: Indonesian PPh Badan: 22%
A14: SECTION 2 — RETURN METRICS
B15: Return on Assets (ROA) | C15: =Net Income / Total Assets | D15: ='Summary PL KONSOL Mei 2026'!F44 | E15: ='Summary BS KONSOL Mei 2026'!F6 | F15: =D15/E15 | G15: ='Summary PL KONSOL Mei 2026'!H44/'Summary BS KONSOL Mei 2026'!I6 | H15: =F15-G15 | I15: ROA >2% = strong for insurance
B16: Return on Equity (ROE) | C16: =Net Income / Total Equity | D16: ='Summary PL KONSOL Mei 2026'!F44 | E16: ='Summary BS KONSOL Mei 2026'!F43 | F16: =D16/E16 | G16: ='Summary PL KONSOL Mei 2026'!H44/'Summary BS KONSOL Mei 2026'!I43 | H16: =F16-G16 | I16: ROE >10% = healthy
B17: Return on Paid-in Capital | C17: =Net Income / Modal Disetor | D17: ='Summary PL KONSOL Mei 2026'!F44 | E17: ='Summary BS KONSOL Mei 2026'!F45 | F17: =D17/E17 | G17: ='Summary PL KONSOL Mei 2026'!H44/'Summary BS KONSOL Mei 2026'!I45 | H17: =F17-G17 | I17: Measures return vs. capital invested
B18: Investment Yield | C18: =Hasil Investasi / Total Assets | D18: ='Summary PL KONSOL Mei 2026'!F26 | E18: ='Summary BS KONSOL Mei 2026'!F6 | F18: =D18/E18 | G18: ='Summary PL KONSOL Mei 2026'!H26/'Summary BS KONSOL Mei 2026'!I6 | H18: =F18-G18 | I18: Yield on invested assets
A20: SECTION 3 — ISLAMIC INSURANCE (TAKAFUL / PENJAMINAN) METRICS
B21: Gross Loss Ratio (Ta'widh Bruto / IJK Bruto) | C21: =Ta'widh Bruto / IJK Bruto | D21: ='Summary PL KONSOL Mei 2026'!F16 | E21: ='Summary PL KONSOL Mei 2026'!F8 | F21: =D21/E21 | G21: ='Summary PL KONSOL Mei 2026'!H16/'Summary PL KONSOL Mei 2026'!H8 | H21: =F21-G21 | I21: Lower = better; >100% = loss-making
B22: Net Claims Ratio | C22: =(Ta'widh Bruto - Reasuransi) / IJK Neto | D22: =('Summary PL KONSOL Mei 2026'!F16+'Summary PL KONSOL Mei 2026'!F17+'Summary PL KONSOL Mei 2026'!F18) | E22: ='Summary PL KONSOL Mei 2026'!F6 | F22: =D22/E22 | G22: N/A | H22: =F22-G22 | I22: Net retained claims / net UW revenue
B23: Recovery Ratio | C23: =Recoveries / Ta'widh Bruto | D23: =ABS('Summary PL KONSOL Mei 2026'!F19) | E23: ='Summary PL KONSOL Mei 2026'!F16 | F23: =D23/E23 | G23: =ABS('Summary PL KONSOL Mei 2026'!H19)/'Summary PL KONSOL Mei 2026'!H16 | H23: =F23-G23 | I23: Higher = better recoveries from debtors
B24: Reinsurance (Cession) Ratio | C24: =Beban PJU / IJK Bruto | D24: =ABS('Summary PL KONSOL Mei 2026'!F9) | E24: ='Summary PL KONSOL Mei 2026'!F8 | F24: =D24/E24 | G24: =ABS('Summary PL KONSOL Mei 2026'!H9)/'Summary PL KONSOL Mei 2026'!H8 | H24: =F24-G24 | I24: % of gross revenue ceded to reinsurer
B25: Net UW Expense Ratio | C25: =Total Beban UW / Hasil UW Neto | D25: ='Summary PL KONSOL Mei 2026'!F14 | E25: ='Summary PL KONSOL Mei 2026'!F24 | F25: =D25/E25 | G25: ='Summary PL KONSOL Mei 2026'!H14/'Summary PL KONSOL Mei 2026'!H24 | H25: =F25-G25 | I25: Operating efficiency of UW book
A27: SECTION 4 — LEVERAGE & CAPITAL ADEQUACY
B28: Debt-to-Equity (D/E) | C28: =Total Liabilities / Total Equity | D28: ='Summary BS KONSOL Mei 2026'!F26 | E28: ='Summary BS KONSOL Mei 2026'!F43 | F28: =D28/E28 | G28: ='Summary BS KONSOL Mei 2026'!I26/'Summary BS KONSOL Mei 2026'!I43 | H28: =F28-G28 | I28: D/E <2.0x preferred for insurance
B29: Financial Leverage Multiplier | C29: =Total Assets / Total Equity | D29: ='Summary BS KONSOL Mei 2026'!F6 | E29: ='Summary BS KONSOL Mei 2026'!F43 | F29: =D29/E29 | G29: ='Summary BS KONSOL Mei 2026'!I6/'Summary BS KONSOL Mei 2026'!I43 | H29: =F29-G29 | I29: DuPont leverage factor
B30: Equity Ratio (Capital Strength) | C30: =Total Equity / Total Assets | D30: ='Summary BS KONSOL Mei 2026'!F43 | E30: ='Summary BS KONSOL Mei 2026'!F6 | F30: =D30/E30 | G30: ='Summary BS KONSOL Mei 2026'!I43/'Summary BS KONSOL Mei 2026'!I6 | H30: =F30-G30 | I30: >30% = well-capitalized
B31: Liabilities-to-Assets | C31: =Total Liabilities / Total Assets | D31: ='Summary BS KONSOL Mei 2026'!F26 | E31: ='Summary BS KONSOL Mei 2026'!F6 | F31: =D31/E31 | G31: ='Summary BS KONSOL Mei 2026'!I26/'Summary BS KONSOL Mei 2026'!I6 | H31: =F31-G31 | I31: <70% generally acceptable
A33: SECTION 5 — ASSET UTILIZATION & GROWTH
B34: Asset Turnover | C34: =IJK Bruto / Total Assets | D34: ='Summary PL KONSOL Mei 2026'!F8 | E34: ='Summary BS KONSOL Mei 2026'!F6 | F34: =D34/E34 | G34: ='Summary PL KONSOL Mei 2026'!H8/'Summary BS KONSOL Mei 2026'!I6 | H34: =F34-G34 | I34: Revenue generated per Rp of assets
B35: Revenue Growth (YoY) | C35: =(Rev26 − Rev25) / Rev25 | D35: ='Summary PL KONSOL Mei 2026'!F8 | E35: ='Summary PL KONSOL Mei 2026'!H8 | F35: =(D35-E35)/E35 | G35: – | H35: =F35-G35 | I35: IJK Bruto YoY growth
B36: Net Income Growth (YoY) | C36: =(NI26 − NI25) / NI25 | D36: ='Summary PL KONSOL Mei 2026'!F44 | E36: ='Summary PL KONSOL Mei 2026'!H44 | F36: =(D36-E36)/E36 | G36: – | H36: =F36-G36 | I36: Bottom-line YoY growth

Sheet CFI_DuPont
A1: JPAS — 5-Factor DuPont ROE Decomposition (CFI FMVA Standard)
A2: All figures in IDR Jutaan | Period: YTD Mei 2026 | 5-Factor: Tax Burden × Interest Burden × EBIT Margin × Asset Turnover × Leverage = ROE
B4: Factor | C4: Formula | D4: Numerator (IDR Juta) | E4: Denominator (IDR Juta) | F4: YTD Mei 2026 | G4: YTD Mei 2025 | H4: Interpretation
A6: ENTER — Source Data (Linked from Financial Statements)
B7: Net Income (Laba Setelah Pajak) | C7: IS Row 44, Col F | D7: ='Summary PL KONSOL Mei 2026'!F44 | E7: ='Summary PL KONSOL Mei 2026'!H44
B8: EBT — Laba Sebelum Pajak | C8: IS Row 40, Col F | D8: ='Summary PL KONSOL Mei 2026'!F40 | E8: ='Summary PL KONSOL Mei 2026'!H40
B9: EBIT — Laba Usaha | C9: IS Row 34, Col F | D9: ='Summary PL KONSOL Mei 2026'!F34 | E9: ='Summary PL KONSOL Mei 2026'!H34
B10: Revenue — IJK Bruto | C10: IS Row 8, Col F | D10: ='Summary PL KONSOL Mei 2026'!F8 | E10: ='Summary PL KONSOL Mei 2026'!H8
B11: Total Assets | C11: BS Row 6, Col F | D11: ='Summary BS KONSOL Mei 2026'!F6 | E11: ='Summary BS KONSOL Mei 2026'!I6
B12: Total Equity | C12: BS Row 43, Col F | D12: ='Summary BS KONSOL Mei 2026'!F43 | E12: ='Summary BS KONSOL Mei 2026'!I43
A14: CALCULATE — 5-Factor DuPont Decomposition
B15: DuPont Factor | C15: Formula Definition | D15: Numerator | E15: Denominator | F15: Mei 2026 | G15: Mei 2025 | H15: Interpretation
B16: Factor 1 — Tax Burden | C16: Net Income / EBT | D16: =D7 | E16: =D8 | F16: =D7/D8 | G16: =E7/E8 | H16: % of EBT retained after tax (1−tax rate)
B17: Factor 2 — Interest Burden | C17: EBT / EBIT | D17: =D8 | E17: =D9 | F17: =D8/D9 | G17: =E8/E9 | H17: % of EBIT after interest & other costs
B18: Factor 3 — EBIT Margin | C18: EBIT / Revenue | D18: =D9 | E18: =D10 | F18: =D9/D10 | G18: =E9/E10 | H18: Operating profitability of each Rp revenue
B19: Factor 4 — Asset Turnover | C19: Revenue / Total Assets | D19: =D10 | E19: =D11 | F19: =D10/D11 | G19: =E10/E11 | H19: Revenue generated per Rp of assets (×)
B20: Factor 5 — Financial Leverage | C20: Total Assets / Equity | D20: =D11 | E20: =D12 | F20: =D11/D12 | G20: =E11/E12 | H20: Leverage amplifier on equity returns (×)
A22: EXIT — ROE Verification (Product Check)
B23: ROE (Direct Calculation) | C23: =Net Income / Total Equity | F23: =D7/D12 | G23: =E7/E12 | H23: Direct formula (benchmark)
B24: ROE (DuPont Product — 5 Factors) | C24: =F1 × F2 × F3 × F4 × F5 | F24: =F16*F17*F18*F19*F20 | G24: =G16*G17*G18*G19*G20 | H24: Must equal ROE Direct ✅
B25: DuPont Check (Direct − Product) | C25: Must equal 0.00% | F25: =F23-F24 | G25: =IF(ABS(F23-F24)<0.0001,"✅ EXACT MATCH","❌ CHECK FORMULAS")
A27: STRATEGIC INTERPRETATION — What Is Driving JPAS ROE?
B28: ↪ Tax Burden ~0.83: | C28: JPAS retains 83% of pre-tax profit → effective tax ~17%. Slightly below statutory 22% = tax incentives likely present.
B29: ↪ Interest Burden ~0.90: | C29: 10% of EBIT is consumed by non-operating costs (other expenses, zakat) before tax.
B30: ↪ EBIT Margin ~24.8%: | C30: Strong operating margin driven by 43% YoY IJK Bruto growth outpacing expense growth.
B31: ↪ Asset Turnover ~0.12x: | C31: Low asset turnover typical of insurance companies — large investment asset base vs. premium revenue.
B32: ↪ Leverage ~2.83x: | C32: Significant leverage: Rp 2.83 of assets deployed per Rp 1 of equity → amplifies ROE but adds risk.
B33: ↪ ROE ~6.2%: | C33: YoY decline from ~6.4% (Mei 2025) despite higher profit, because equity base grew faster (new capital / retained earnings).
